{
  "sim_date": "2026-06-04",
  "day_number": 4,
  "agent_id": "1b6f9b63-1c87-4f6b-a663-d89b5fe26302",
  "agent_name": "Mei Petrov",
  "status": "ready",
  "beats": [
    {
      "index": 0,
      "start_time": "2026-06-04T14:00:00.000Z",
      "end_time": "2026-06-04T14:23:41.304Z",
      "activity": "Wake up, coffee, check weather and transit strike updates, prepare for bike commute.",
      "activity_type": "home",
      "location_name": "Home (Wallingford)",
      "location": [
        -122.332,
        47.6605
      ],
      "travel_from_prev": null,
      "reasoning": "Early riser who values planning; the transit strike means she'll bike instead, so she checks conditions before heading out. Organized enough to prep deliberately."
    },
    {
      "index": 1,
      "start_time": "2026-06-04T14:39:41.304Z",
      "end_time": "2026-06-04T15:06:45.652Z",
      "activity": "Bike commute downtown through Wallingford and Capitol Hill to the shop.",
      "activity_type": "commute",
      "location_name": "Downtown Seattle",
      "location": [
        -122.33449,
        47.604458
      ],
      "travel_from_prev": {
        "mode": "driving",
        "polyline": [
          [
            -122.332002,
            47.660291
          ],
          [
            -122.331886,
            47.660291
          ],
          [
            -122.331483,
            47.660289
          ],
          [
            -122.331449,
            47.660289
          ],
          [
            -122.33145,
            47.660283
          ],
          [
            -122.331444,
            47.66027
          ],
          [
            -122.331433,
            47.660259
          ],
          [
            -122.331418,
            47.660251
          ],
          [
            -122.331399,
            47.660247
          ],
          [
            -122.331388,
            47.660246
          ],
          [
            -122.331379,
            47.660246
          ],
          [
            -122.33136,
            47.66025
          ],
          [
            -122.331344,
            47.660258
          ],
          [
            -122.331332,
            47.66027
          ],
          [
            -122.331326,
            47.660283
          ],
          [
            -122.331326,
            47.660288
          ],
          [
            -122.331327,
            47.660298
          ],
          [
            -122.331336,
            47.660311
          ],
          [
            -122.33135,
            47.660321
          ],
          [
            -122.331369,
            47.660328
          ],
          [
            -122.331381,
            47.660329
          ],
          [
            -122.33138,
            47.660356
          ],
          [
            -122.331373,
            47.661301
          ],
          [
            -122.331372,
            47.661363
          ],
          [
            -122.331255,
            47.661363
          ],
          [
            -122.331177,
            47.661363
          ],
          [
            -122.33108,
            47.661363
          ],
          [
            -122.330901,
            47.661362
          ],
          [
            -122.330486,
            47.661362
          ],
          [
            -122.33017,
            47.661362
          ],
          [
            -122.330097,
            47.661362
          ],
          [
            -122.328981,
            47.66136
          ],
          [
            -122.328256,
            47.661358
          ],
          [
            -122.328218,
            47.661358
          ],
          [
            -122.328036,
            47.661358
          ],
          [
            -122.327962,
            47.661358
          ],
          [
            -122.327515,
            47.661357
          ],
          [
            -122.327338,
            47.661357
          ],
          [
            -122.327261,
            47.661357
          ],
          [
            -122.326883,
            47.661356
          ],
          [
            -122.326496,
            47.661355
          ],
          [
            -122.326433,
            47.661355
          ],
          [
            -122.326301,
            47.661354
          ],
          [
            -122.326207,
            47.661354
          ],
          [
            -122.326088,
            47.661354
          ],
          [
            -122.325776,
            47.661354
          ],
          [
            -122.325695,
            47.661353
          ],
          [
            -122.325417,
            47.661353
          ],
          [
            -122.32522,
            47.661353
          ],
          [
            -122.325115,
            47.661353
          ],
          [
            -122.325015,
            47.661352
          ],
          [
            -122.324926,
            47.661352
          ],
          [
            -122.324155,
            47.66135
          ],
          [
            -122.324043,
            47.66135
          ],
          [
            -122.323383,
            47.661345
          ],
          [
            -122.323018,
            47.661342
          ],
          [
            -122.322863,
            47.66134
          ],
          [
            -122.322913,
            47.661205
          ],
          [
            -122.322918,
            47.661162
          ],
          [
            -122.32293,
            47.661057
          ],
          [
            -122.322945,
            47.660866
          ],
          [
            -122.322947,
            47.660578
          ],
          [
            -122.32295,
            47.660198
          ],
          [
            -122.322931,
            47.660129
          ],
          [
            -122.322857,
            47.65986
          ],
          [
            -122.322855,
            47.659251
          ],
          [
            -122.322869,
            47.658689
          ],
          [
            -122.322856,
            47.658279
          ],
          [
            -122.322834,
            47.658023
          ],
          [
            -122.322647,
            47.657466
          ],
          [
            -122.322615,
            47.65701
          ],
          [
            -122.32259,
            47.656657
          ],
          [
            -122.32258,
            47.655751
          ],
          [
            -122.322668,
            47.651159
          ],
          [
            -122.322699,
            47.64922
          ],
          [
            -122.322709,
            47.64868
          ],
          [
            -122.322751,
            47.648064
          ],
          [
            -122.322774,
            47.647758
          ],
          [
            -122.322893,
            47.646706
          ],
          [
            -122.322993,
            47.645834
          ],
          [
            -122.323038,
            47.645443
          ],
          [
            -122.323085,
            47.64489
          ],
          [
            -122.323107,
            47.64455
          ],
          [
            -122.323107,
            47.644547
          ],
          [
            -122.323178,
            47.643463
          ],
          [
            -122.323227,
            47.642714
          ],
          [
            -122.323262,
            47.641839
          ],
          [
            -122.323276,
            47.641325
          ],
          [
            -122.323278,
            47.64042
          ],
          [
            -122.323281,
            47.639459
          ],
          [
            -122.32325,
            47.638202
          ],
          [
            -122.323265,
            47.637304
          ],
          [
            -122.323269,
            47.637071
          ],
          [
            -122.323285,
            47.636837
          ],
          [
            -122.323306,
            47.636604
          ],
          [
            -122.32331,
            47.636573
          ],
          [
            -122.323333,
            47.63637
          ],
          [
            -122.323366,
            47.636137
          ],
          [
            -122.323405,
            47.635905
          ],
          [
            -122.32345,
            47.635672
          ],
          [
            -122.323501,
            47.635441
          ],
          [
            -122.323557,
            47.63521
          ],
          [
            -122.323619,
            47.634979
          ],
          [
            -122.323653,
            47.634859
          ],
          [
            -122.323687,
            47.63475
          ],
          [
            -122.32376,
            47.634521
          ],
          [
            -122.32384,
            47.634293
          ],
          [
            -122.324055,
            47.633772
          ],
          [
            -122.324447,
            47.632829
          ],
          [
            -122.324505,
            47.632692
          ],
          [
            -122.32457,
            47.632556
          ],
          [
            -122.324642,
            47.632421
          ],
          [
            -122.324719,
            47.632288
          ],
          [
            -122.324804,
            47.632157
          ],
          [
            -122.324894,
            47.632028
          ],
          [
            -122.324991,
            47.631901
          ],
          [
            -122.325093,
            47.631776
          ],
          [
            -122.325202,
            47.631653
          ],
          [
            -122.325316,
            47.631532
          ],
          [
            -122.325436,
            47.631415
          ],
          [
            -122.325562,
            47.6313
          ],
          [
            -122.326661,
            47.63031
          ],
          [
            -122.326857,
            47.630131
          ],
          [
            -122.327462,
            47.629581
          ],
          [
            -122.327565,
            47.629474
          ],
          [
            -122.327664,
            47.629364
          ],
          [
            -122.327759,
            47.629253
          ],
          [
            -122.327849,
            47.62914
          ],
          [
            -122.327936,
            47.629026
          ],
          [
            -122.328018,
            47.628911
          ],
          [
            -122.328095,
            47.628794
          ],
          [
            -122.328168,
            47.628676
          ],
          [
            -122.328237,
            47.628556
          ],
          [
            -122.328302,
            47.628436
          ],
          [
            -122.328361,
            47.628314
          ],
          [
            -122.328417,
            47.628192
          ],
          [
            -122.328467,
            47.628068
          ],
          [
            -122.328513,
            47.627944
          ],
          [
            -122.328555,
            47.627819
          ],
          [
            -122.328591,
            47.627693
          ],
          [
            -122.328623,
            47.627567
          ],
          [
            -122.32865,
            47.62744
          ],
          [
            -122.328673,
            47.627313
          ],
          [
            -122.328691,
            47.627185
          ],
          [
            -122.328704,
            47.627058
          ],
          [
            -122.328712,
            47.62693
          ],
          [
            -122.328715,
            47.626801
          ],
          [
            -122.328714,
            47.626673
          ],
          [
            -122.328677,
            47.623423
          ],
          [
            -122.328676,
            47.623262
          ],
          [
            -122.328669,
            47.621878
          ],
          [
            -122.328669,
            47.621868
          ],
          [
            -122.328669,
            47.621856
          ],
          [
            -122.328665,
            47.621548
          ],
          [
            -122.328664,
            47.621191
          ],
          [
            -122.328661,
            47.620828
          ],
          [
            -122.328659,
            47.620563
          ],
          [
            -122.328651,
            47.620224
          ],
          [
            -122.328634,
            47.619538
          ],
          [
            -122.328644,
            47.619159
          ],
          [
            -122.328666,
            47.61884
          ],
          [
            -122.328691,
            47.618583
          ],
          [
            -122.328704,
            47.618458
          ],
          [
            -122.328742,
            47.618166
          ],
          [
            -122.328751,
            47.61809
          ],
          [
            -122.328781,
            47.617907
          ],
          [
            -122.328814,
            47.617724
          ],
          [
            -122.32885,
            47.617541
          ],
          [
            -122.328891,
            47.617358
          ],
          [
            -122.328935,
            47.617176
          ],
          [
            -122.328983,
            47.616994
          ],
          [
            -122.32903,
            47.61682
          ],
          [
            -122.329058,
            47.616716
          ],
          [
            -122.329084,
            47.616623
          ],
          [
            -122.329177,
            47.61634
          ],
          [
            -122.329201,
            47.616271
          ],
          [
            -122.329234,
            47.616178
          ],
          [
            -122.329252,
            47.616127
          ],
          [
            -122.329326,
            47.615929
          ],
          [
            -122.329331,
            47.615916
          ],
          [
            -122.32941,
            47.615721
          ],
          [
            -122.329539,
            47.615422
          ],
          [
            -122.329691,
            47.615071
          ],
          [
            -122.329832,
            47.614746
          ],
          [
            -122.32986,
            47.61468
          ],
          [
            -122.330028,
            47.614272
          ],
          [
            -122.330034,
            47.614258
          ],
          [
            -122.330049,
            47.614222
          ],
          [
            -122.330056,
            47.614206
          ],
          [
            -122.330103,
            47.61409
          ],
          [
            -122.330175,
            47.613917
          ],
          [
            -122.330378,
            47.613434
          ],
          [
            -122.330455,
            47.613249
          ],
          [
            -122.330597,
            47.612889
          ],
          [
            -122.3306,
            47.61288
          ],
          [
            -122.331202,
            47.611262
          ],
          [
            -122.331246,
            47.611128
          ],
          [
            -122.331254,
            47.611103
          ],
          [
            -122.331296,
            47.610952
          ],
          [
            -122.331301,
            47.610933
          ],
          [
            -122.331364,
            47.610629
          ],
          [
            -122.331375,
            47.610566
          ],
          [
            -122.331417,
            47.610459
          ],
          [
            -122.331549,
            47.610125
          ],
          [
            -122.331566,
            47.610048
          ],
          [
            -122.331573,
            47.609972
          ],
          [
            -122.33157,
            47.609813
          ],
          [
            -122.331566,
            47.609667
          ],
          [
            -122.331565,
            47.60965
          ],
          [
            -122.331552,
            47.609484
          ],
          [
            -122.331508,
            47.608979
          ],
          [
            -122.331462,
            47.608543
          ],
          [
            -122.3314,
            47.608293
          ],
          [
            -122.331313,
            47.60804
          ],
          [
            -122.331201,
            47.607838
          ],
          [
            -122.331055,
            47.607631
          ],
          [
            -122.329687,
            47.606053
          ],
          [
            -122.32944,
            47.605754
          ],
          [
            -122.329322,
            47.605611
          ],
          [
            -122.329334,
            47.605606
          ],
          [
            -122.329464,
            47.60555
          ],
          [
            -122.32983,
            47.6054
          ],
          [
            -122.329969,
            47.605343
          ],
          [
            -122.330404,
            47.605164
          ],
          [
            -122.330527,
            47.605114
          ],
          [
            -122.330594,
            47.605086
          ],
          [
            -122.33107,
            47.604892
          ],
          [
            -122.33116,
            47.604855
          ],
          [
            -122.331316,
            47.604791
          ],
          [
            -122.331496,
            47.604717
          ],
          [
            -122.331609,
            47.604672
          ],
          [
            -122.331683,
            47.60475
          ],
          [
            -122.332043,
            47.605127
          ],
          [
            -122.332214,
            47.605305
          ],
          [
            -122.332271,
            47.605365
          ],
          [
            -122.332341,
            47.605443
          ],
          [
            -122.332781,
            47.605939
          ],
          [
            -122.332855,
            47.606022
          ],
          [
            -122.332858,
            47.606025
          ],
          [
            -122.332913,
            47.606086
          ],
          [
            -122.332975,
            47.606061
          ],
          [
            -122.33305,
            47.60603
          ],
          [
            -122.333927,
            47.60567
          ],
          [
            -122.334026,
            47.605629
          ],
          [
            -122.334131,
            47.605584
          ],
          [
            -122.334593,
            47.605387
          ],
          [
            -122.334878,
            47.605265
          ],
          [
            -122.334997,
            47.605214
          ],
          [
            -122.335058,
            47.605189
          ],
          [
            -122.33513,
            47.605157
          ],
          [
            -122.335074,
            47.605097
          ],
          [
            -122.334663,
            47.604648
          ],
          [
            -122.334622,
            47.604603
          ],
          [
            -122.334546,
            47.604521
          ],
          [
            -122.334488,
            47.604457
          ]
        ],
        "duration_minutes": 16
      },
      "reasoning": "Transit strike forces her to cycle; she's a mechanic who prefers biking anyway. Mild 68°F weather is perfect for an early ride. Generously budgeted 40 min for Capitol Hill routing."
    },
    {
      "index": 2,
      "start_time": "2026-06-04T15:06:45.652Z",
      "end_time": "2026-06-04T17:59:20.869Z",
      "activity": "Work at the bike shop: tune-ups, repairs, customer consultations, restocking.",
      "activity_type": "work",
      "location_name": "Downtown Seattle",
      "location": [
        -122.33449,
        47.604458
      ],
      "travel_from_prev": null,
      "reasoning": "Thursday morning at the shop is steady work. She's organized and methodical; would tackle repairs and inventory during the strike when fewer people can easily get around."
    },
    {
      "index": 3,
      "start_time": "2026-06-04T18:11:20.869Z",
      "end_time": "2026-06-04T18:38:25.217Z",
      "activity": "Bike to Pike Place Market for lunch, grab fresh greens and water.",
      "activity_type": "meal",
      "location_name": "Pike Place Market (Downtown Seattle)",
      "location": [
        -122.3422,
        47.6097
      ],
      "travel_from_prev": {
        "mode": "walking",
        "polyline": [
          [
            -122.334488,
            47.604457
          ],
          [
            -122.334546,
            47.604521
          ],
          [
            -122.334649,
            47.604479
          ],
          [
            -122.334686,
            47.604465
          ],
          [
            -122.335065,
            47.604887
          ],
          [
            -122.335208,
            47.605042
          ],
          [
            -122.335221,
            47.605056
          ],
          [
            -122.335238,
            47.605073
          ],
          [
            -122.335266,
            47.605101
          ],
          [
            -122.33532,
            47.605156
          ],
          [
            -122.335335,
            47.605173
          ],
          [
            -122.335346,
            47.605174
          ],
          [
            -122.335871,
            47.605742
          ],
          [
            -122.335881,
            47.605743
          ],
          [
            -122.335887,
            47.605751
          ],
          [
            -122.335899,
            47.605764
          ],
          [
            -122.335934,
            47.605811
          ],
          [
            -122.335969,
            47.605859
          ],
          [
            -122.335989,
            47.605878
          ],
          [
            -122.335973,
            47.605885
          ],
          [
            -122.336521,
            47.606472
          ],
          [
            -122.336524,
            47.606475
          ],
          [
            -122.336543,
            47.606496
          ],
          [
            -122.336572,
            47.606526
          ],
          [
            -122.336621,
            47.606575
          ],
          [
            -122.33664,
            47.606597
          ],
          [
            -122.337175,
            47.607179
          ],
          [
            -122.337172,
            47.60719
          ],
          [
            -122.337191,
            47.607211
          ],
          [
            -122.337212,
            47.607249
          ],
          [
            -122.337243,
            47.607306
          ],
          [
            -122.337279,
            47.60731
          ],
          [
            -122.338061,
            47.608167
          ],
          [
            -122.338088,
            47.608174
          ],
          [
            -122.338094,
            47.60819
          ],
          [
            -122.338141,
            47.608234
          ],
          [
            -122.338194,
            47.608283
          ],
          [
            -122.338211,
            47.608299
          ],
          [
            -122.338206,
            47.608311
          ],
          [
            -122.338965,
            47.609143
          ],
          [
            -122.338992,
            47.60917
          ],
          [
            -122.339016,
            47.609171
          ],
          [
            -122.339045,
            47.609159
          ],
          [
            -122.339405,
            47.609005
          ],
          [
            -122.3398,
            47.608838
          ],
          [
            -122.339825,
            47.608865
          ],
          [
            -122.33986,
            47.608903
          ],
          [
            -122.339881,
            47.608926
          ],
          [
            -122.339904,
            47.608948
          ],
          [
            -122.339934,
            47.608936
          ],
          [
            -122.339975,
            47.608942
          ],
          [
            -122.34,
            47.608931
          ],
          [
            -122.340066,
            47.608917
          ],
          [
            -122.340281,
            47.60887
          ],
          [
            -122.340294,
            47.608885
          ],
          [
            -122.340299,
            47.608892
          ],
          [
            -122.340547,
            47.608787
          ],
          [
            -122.340565,
            47.608781
          ],
          [
            -122.340605,
            47.608802
          ],
          [
            -122.340641,
            47.608824
          ],
          [
            -122.340871,
            47.608966
          ],
          [
            -122.341021,
            47.609056
          ],
          [
            -122.341059,
            47.609078
          ],
          [
            -122.341099,
            47.609102
          ],
          [
            -122.341102,
            47.609103
          ],
          [
            -122.341428,
            47.609301
          ],
          [
            -122.34156,
            47.609378
          ],
          [
            -122.341631,
            47.60942
          ],
          [
            -122.34164,
            47.609425
          ],
          [
            -122.341646,
            47.609437
          ],
          [
            -122.341671,
            47.609437
          ],
          [
            -122.341758,
            47.609482
          ],
          [
            -122.341829,
            47.609517
          ],
          [
            -122.341829,
            47.609523
          ],
          [
            -122.341829,
            47.609535
          ],
          [
            -122.341841,
            47.609537
          ],
          [
            -122.342009,
            47.609639
          ],
          [
            -122.342013,
            47.609647
          ],
          [
            -122.342023,
            47.609648
          ],
          [
            -122.342046,
            47.609649
          ],
          [
            -122.342106,
            47.609683
          ],
          [
            -122.342195,
            47.60973
          ]
        ],
        "duration_minutes": 12
      },
      "reasoning": "She loves Pike Place and visited yesterday; it's a short ride from the shop. Mild weather means outdoor eating is pleasant. Repeating the salad pattern shows her preference for hydration on pleasant days."
    },
    {
      "index": 4,
      "start_time": "2026-06-04T18:50:25.217Z",
      "end_time": "2026-06-04T19:10:43.478Z",
      "activity": "Ride back to the bike shop.",
      "activity_type": "commute",
      "location_name": "Downtown Seattle",
      "location": [
        -122.33449,
        47.604458
      ],
      "travel_from_prev": {
        "mode": "walking",
        "polyline": [
          [
            -122.342195,
            47.60973
          ],
          [
            -122.342106,
            47.609683
          ],
          [
            -122.342046,
            47.609649
          ],
          [
            -122.342023,
            47.609648
          ],
          [
            -122.342013,
            47.609647
          ],
          [
            -122.342009,
            47.609639
          ],
          [
            -122.341841,
            47.609537
          ],
          [
            -122.341829,
            47.609535
          ],
          [
            -122.341829,
            47.609523
          ],
          [
            -122.341829,
            47.609517
          ],
          [
            -122.341758,
            47.609482
          ],
          [
            -122.341671,
            47.609437
          ],
          [
            -122.341646,
            47.609437
          ],
          [
            -122.34164,
            47.609425
          ],
          [
            -122.341631,
            47.60942
          ],
          [
            -122.34156,
            47.609378
          ],
          [
            -122.341428,
            47.609301
          ],
          [
            -122.341102,
            47.609103
          ],
          [
            -122.341099,
            47.609102
          ],
          [
            -122.341059,
            47.609078
          ],
          [
            -122.341021,
            47.609056
          ],
          [
            -122.340871,
            47.608966
          ],
          [
            -122.340641,
            47.608824
          ],
          [
            -122.340605,
            47.608802
          ],
          [
            -122.340565,
            47.608781
          ],
          [
            -122.340547,
            47.608787
          ],
          [
            -122.340299,
            47.608892
          ],
          [
            -122.340294,
            47.608885
          ],
          [
            -122.340281,
            47.60887
          ],
          [
            -122.340066,
            47.608917
          ],
          [
            -122.34,
            47.608931
          ],
          [
            -122.339975,
            47.608942
          ],
          [
            -122.339934,
            47.608936
          ],
          [
            -122.339904,
            47.608948
          ],
          [
            -122.339881,
            47.608926
          ],
          [
            -122.33986,
            47.608903
          ],
          [
            -122.339825,
            47.608865
          ],
          [
            -122.3398,
            47.608838
          ],
          [
            -122.339405,
            47.609005
          ],
          [
            -122.339045,
            47.609159
          ],
          [
            -122.339016,
            47.609171
          ],
          [
            -122.338992,
            47.60917
          ],
          [
            -122.338965,
            47.609143
          ],
          [
            -122.338206,
            47.608311
          ],
          [
            -122.338211,
            47.608299
          ],
          [
            -122.338194,
            47.608283
          ],
          [
            -122.338141,
            47.608234
          ],
          [
            -122.338094,
            47.60819
          ],
          [
            -122.338088,
            47.608174
          ],
          [
            -122.338061,
            47.608167
          ],
          [
            -122.337279,
            47.60731
          ],
          [
            -122.337243,
            47.607306
          ],
          [
            -122.337212,
            47.607249
          ],
          [
            -122.337191,
            47.607211
          ],
          [
            -122.337172,
            47.60719
          ],
          [
            -122.337175,
            47.607179
          ],
          [
            -122.33664,
            47.606597
          ],
          [
            -122.336621,
            47.606575
          ],
          [
            -122.336572,
            47.606526
          ],
          [
            -122.336543,
            47.606496
          ],
          [
            -122.336524,
            47.606475
          ],
          [
            -122.336521,
            47.606472
          ],
          [
            -122.335973,
            47.605885
          ],
          [
            -122.335989,
            47.605878
          ],
          [
            -122.335969,
            47.605859
          ],
          [
            -122.335934,
            47.605811
          ],
          [
            -122.335899,
            47.605764
          ],
          [
            -122.335887,
            47.605751
          ],
          [
            -122.335881,
            47.605743
          ],
          [
            -122.335871,
            47.605742
          ],
          [
            -122.335346,
            47.605174
          ],
          [
            -122.335335,
            47.605173
          ],
          [
            -122.33532,
            47.605156
          ],
          [
            -122.335266,
            47.605101
          ],
          [
            -122.335238,
            47.605073
          ],
          [
            -122.335221,
            47.605056
          ],
          [
            -122.335208,
            47.605042
          ],
          [
            -122.335065,
            47.604887
          ],
          [
            -122.334686,
            47.604465
          ],
          [
            -122.334649,
            47.604479
          ],
          [
            -122.334546,
            47.604521
          ],
          [
            -122.334488,
            47.604457
          ]
        ],
        "duration_minutes": 12
      },
      "reasoning": "Short commute back to work. Transit strike still in effect (ends at 4pm), so she continues by bike."
    },
    {
      "index": 5,
      "start_time": "2026-06-04T19:10:43.478Z",
      "end_time": "2026-06-04T20:45:28.695Z",
      "activity": "Afternoon shop work: more repairs, tune-ups, and helping customers navigate bike choices.",
      "activity_type": "work",
      "location_name": "Downtown Seattle",
      "location": [
        -122.33449,
        47.604458
      ],
      "travel_from_prev": null,
      "reasoning": "Afternoon shift continues steady work. By 4pm the transit strike ends, but she's already on her bike schedule for the day."
    },
    {
      "index": 6,
      "start_time": "2026-06-04T21:01:28.695Z",
      "end_time": "2026-06-04T21:31:56.086Z",
      "activity": "Bike home through Capitol Hill and Wallingford, enjoying the mild evening light.",
      "activity_type": "commute",
      "location_name": "Home (Wallingford)",
      "location": [
        -122.332,
        47.6605
      ],
      "travel_from_prev": {
        "mode": "driving",
        "polyline": [
          [
            -122.334488,
            47.604457
          ],
          [
            -122.334546,
            47.604521
          ],
          [
            -122.334622,
            47.604603
          ],
          [
            -122.334663,
            47.604648
          ],
          [
            -122.335074,
            47.605097
          ],
          [
            -122.33513,
            47.605157
          ],
          [
            -122.335058,
            47.605189
          ],
          [
            -122.334997,
            47.605214
          ],
          [
            -122.334878,
            47.605265
          ],
          [
            -122.334593,
            47.605387
          ],
          [
            -122.334131,
            47.605584
          ],
          [
            -122.334026,
            47.605629
          ],
          [
            -122.333927,
            47.60567
          ],
          [
            -122.33305,
            47.60603
          ],
          [
            -122.332975,
            47.606061
          ],
          [
            -122.332913,
            47.606086
          ],
          [
            -122.332858,
            47.606025
          ],
          [
            -122.332855,
            47.606022
          ],
          [
            -122.332781,
            47.605939
          ],
          [
            -122.332341,
            47.605443
          ],
          [
            -122.332271,
            47.605365
          ],
          [
            -122.332214,
            47.605305
          ],
          [
            -122.332043,
            47.605127
          ],
          [
            -122.331683,
            47.60475
          ],
          [
            -122.331609,
            47.604672
          ],
          [
            -122.331496,
            47.604717
          ],
          [
            -122.331316,
            47.604791
          ],
          [
            -122.33116,
            47.604855
          ],
          [
            -122.33107,
            47.604892
          ],
          [
            -122.330594,
            47.605086
          ],
          [
            -122.330527,
            47.605114
          ],
          [
            -122.330404,
            47.605164
          ],
          [
            -122.329969,
            47.605343
          ],
          [
            -122.32983,
            47.6054
          ],
          [
            -122.329464,
            47.60555
          ],
          [
            -122.329334,
            47.605606
          ],
          [
            -122.329322,
            47.605611
          ],
          [
            -122.32944,
            47.605754
          ],
          [
            -122.329687,
            47.606053
          ],
          [
            -122.331055,
            47.607631
          ],
          [
            -122.331201,
            47.607838
          ],
          [
            -122.331313,
            47.60804
          ],
          [
            -122.3314,
            47.608293
          ],
          [
            -122.331462,
            47.608543
          ],
          [
            -122.331508,
            47.608979
          ],
          [
            -122.331552,
            47.609484
          ],
          [
            -122.331565,
            47.60965
          ],
          [
            -122.331566,
            47.609667
          ],
          [
            -122.33157,
            47.609813
          ],
          [
            -122.331573,
            47.609972
          ],
          [
            -122.331566,
            47.610048
          ],
          [
            -122.331549,
            47.610125
          ],
          [
            -122.331417,
            47.610459
          ],
          [
            -122.331375,
            47.610566
          ],
          [
            -122.331364,
            47.610629
          ],
          [
            -122.331301,
            47.610933
          ],
          [
            -122.331296,
            47.610952
          ],
          [
            -122.331254,
            47.611103
          ],
          [
            -122.331246,
            47.611128
          ],
          [
            -122.331202,
            47.611262
          ],
          [
            -122.3306,
            47.61288
          ],
          [
            -122.330597,
            47.612889
          ],
          [
            -122.330455,
            47.613249
          ],
          [
            -122.330378,
            47.613434
          ],
          [
            -122.330175,
            47.613917
          ],
          [
            -122.330103,
            47.61409
          ],
          [
            -122.330056,
            47.614206
          ],
          [
            -122.330049,
            47.614222
          ],
          [
            -122.330034,
            47.614258
          ],
          [
            -122.330028,
            47.614272
          ],
          [
            -122.32986,
            47.61468
          ],
          [
            -122.329832,
            47.614746
          ],
          [
            -122.329691,
            47.615071
          ],
          [
            -122.329539,
            47.615422
          ],
          [
            -122.32941,
            47.615721
          ],
          [
            -122.329331,
            47.615916
          ],
          [
            -122.329326,
            47.615929
          ],
          [
            -122.329252,
            47.616127
          ],
          [
            -122.329234,
            47.616178
          ],
          [
            -122.329201,
            47.616271
          ],
          [
            -122.329177,
            47.61634
          ],
          [
            -122.329084,
            47.616623
          ],
          [
            -122.329058,
            47.616716
          ],
          [
            -122.32903,
            47.61682
          ],
          [
            -122.328983,
            47.616994
          ],
          [
            -122.328935,
            47.617176
          ],
          [
            -122.328891,
            47.617358
          ],
          [
            -122.32885,
            47.617541
          ],
          [
            -122.328814,
            47.617724
          ],
          [
            -122.328781,
            47.617907
          ],
          [
            -122.328751,
            47.61809
          ],
          [
            -122.328742,
            47.618166
          ],
          [
            -122.328704,
            47.618458
          ],
          [
            -122.328691,
            47.618583
          ],
          [
            -122.328666,
            47.61884
          ],
          [
            -122.328644,
            47.619159
          ],
          [
            -122.328634,
            47.619538
          ],
          [
            -122.328651,
            47.620224
          ],
          [
            -122.328659,
            47.620563
          ],
          [
            -122.328661,
            47.620828
          ],
          [
            -122.328664,
            47.621191
          ],
          [
            -122.328665,
            47.621548
          ],
          [
            -122.328669,
            47.621856
          ],
          [
            -122.328669,
            47.621868
          ],
          [
            -122.328669,
            47.621878
          ],
          [
            -122.328676,
            47.623262
          ],
          [
            -122.328677,
            47.623423
          ],
          [
            -122.328714,
            47.626673
          ],
          [
            -122.328715,
            47.626801
          ],
          [
            -122.328712,
            47.62693
          ],
          [
            -122.328704,
            47.627058
          ],
          [
            -122.328691,
            47.627185
          ],
          [
            -122.328673,
            47.627313
          ],
          [
            -122.32865,
            47.62744
          ],
          [
            -122.328623,
            47.627567
          ],
          [
            -122.328591,
            47.627693
          ],
          [
            -122.328555,
            47.627819
          ],
          [
            -122.328513,
            47.627944
          ],
          [
            -122.328467,
            47.628068
          ],
          [
            -122.328417,
            47.628192
          ],
          [
            -122.328361,
            47.628314
          ],
          [
            -122.328302,
            47.628436
          ],
          [
            -122.328237,
            47.628556
          ],
          [
            -122.328168,
            47.628676
          ],
          [
            -122.328095,
            47.628794
          ],
          [
            -122.328018,
            47.628911
          ],
          [
            -122.327936,
            47.629026
          ],
          [
            -122.327849,
            47.62914
          ],
          [
            -122.327759,
            47.629253
          ],
          [
            -122.327664,
            47.629364
          ],
          [
            -122.327565,
            47.629474
          ],
          [
            -122.327462,
            47.629581
          ],
          [
            -122.326857,
            47.630131
          ],
          [
            -122.326661,
            47.63031
          ],
          [
            -122.325562,
            47.6313
          ],
          [
            -122.325436,
            47.631415
          ],
          [
            -122.325316,
            47.631532
          ],
          [
            -122.325202,
            47.631653
          ],
          [
            -122.325093,
            47.631776
          ],
          [
            -122.324991,
            47.631901
          ],
          [
            -122.324894,
            47.632028
          ],
          [
            -122.324804,
            47.632157
          ],
          [
            -122.324719,
            47.632288
          ],
          [
            -122.324642,
            47.632421
          ],
          [
            -122.32457,
            47.632556
          ],
          [
            -122.324505,
            47.632692
          ],
          [
            -122.324447,
            47.632829
          ],
          [
            -122.324055,
            47.633772
          ],
          [
            -122.32384,
            47.634293
          ],
          [
            -122.32376,
            47.634521
          ],
          [
            -122.323687,
            47.63475
          ],
          [
            -122.323653,
            47.634859
          ],
          [
            -122.323619,
            47.634979
          ],
          [
            -122.323557,
            47.63521
          ],
          [
            -122.323501,
            47.635441
          ],
          [
            -122.32345,
            47.635672
          ],
          [
            -122.323405,
            47.635905
          ],
          [
            -122.323366,
            47.636137
          ],
          [
            -122.323333,
            47.63637
          ],
          [
            -122.32331,
            47.636573
          ],
          [
            -122.323306,
            47.636604
          ],
          [
            -122.323285,
            47.636837
          ],
          [
            -122.323269,
            47.637071
          ],
          [
            -122.323265,
            47.637304
          ],
          [
            -122.32325,
            47.638202
          ],
          [
            -122.323281,
            47.639459
          ],
          [
            -122.323278,
            47.64042
          ],
          [
            -122.323276,
            47.641325
          ],
          [
            -122.323262,
            47.641839
          ],
          [
            -122.323227,
            47.642714
          ],
          [
            -122.323178,
            47.643463
          ],
          [
            -122.323107,
            47.644547
          ],
          [
            -122.323107,
            47.64455
          ],
          [
            -122.323085,
            47.64489
          ],
          [
            -122.323038,
            47.645443
          ],
          [
            -122.322993,
            47.645834
          ],
          [
            -122.322893,
            47.646706
          ],
          [
            -122.322774,
            47.647758
          ],
          [
            -122.322751,
            47.648064
          ],
          [
            -122.322709,
            47.64868
          ],
          [
            -122.322699,
            47.64922
          ],
          [
            -122.322668,
            47.651159
          ],
          [
            -122.32258,
            47.655751
          ],
          [
            -122.32259,
            47.656657
          ],
          [
            -122.322615,
            47.65701
          ],
          [
            -122.322647,
            47.657466
          ],
          [
            -122.322834,
            47.658023
          ],
          [
            -122.322856,
            47.658279
          ],
          [
            -122.322869,
            47.658689
          ],
          [
            -122.322855,
            47.659251
          ],
          [
            -122.322857,
            47.65986
          ],
          [
            -122.322931,
            47.660129
          ],
          [
            -122.32295,
            47.660198
          ],
          [
            -122.322947,
            47.660578
          ],
          [
            -122.322945,
            47.660866
          ],
          [
            -122.32293,
            47.661057
          ],
          [
            -122.322918,
            47.661162
          ],
          [
            -122.322913,
            47.661205
          ],
          [
            -122.322863,
            47.66134
          ],
          [
            -122.323018,
            47.661342
          ],
          [
            -122.323383,
            47.661345
          ],
          [
            -122.324043,
            47.66135
          ],
          [
            -122.324155,
            47.66135
          ],
          [
            -122.324926,
            47.661352
          ],
          [
            -122.325015,
            47.661352
          ],
          [
            -122.325115,
            47.661353
          ],
          [
            -122.32522,
            47.661353
          ],
          [
            -122.325417,
            47.661353
          ],
          [
            -122.325695,
            47.661353
          ],
          [
            -122.325776,
            47.661354
          ],
          [
            -122.326088,
            47.661354
          ],
          [
            -122.326207,
            47.661354
          ],
          [
            -122.326301,
            47.661354
          ],
          [
            -122.326433,
            47.661355
          ],
          [
            -122.326496,
            47.661355
          ],
          [
            -122.326883,
            47.661356
          ],
          [
            -122.327261,
            47.661357
          ],
          [
            -122.327338,
            47.661357
          ],
          [
            -122.327515,
            47.661357
          ],
          [
            -122.327962,
            47.661358
          ],
          [
            -122.328036,
            47.661358
          ],
          [
            -122.328218,
            47.661358
          ],
          [
            -122.328256,
            47.661358
          ],
          [
            -122.328981,
            47.66136
          ],
          [
            -122.330097,
            47.661362
          ],
          [
            -122.33017,
            47.661362
          ],
          [
            -122.330486,
            47.661362
          ],
          [
            -122.330901,
            47.661362
          ],
          [
            -122.33108,
            47.661363
          ],
          [
            -122.331177,
            47.661363
          ],
          [
            -122.331255,
            47.661363
          ],
          [
            -122.331372,
            47.661363
          ],
          [
            -122.331373,
            47.661301
          ],
          [
            -122.33138,
            47.660356
          ],
          [
            -122.331381,
            47.660329
          ],
          [
            -122.331369,
            47.660328
          ],
          [
            -122.33135,
            47.660321
          ],
          [
            -122.331336,
            47.660311
          ],
          [
            -122.331327,
            47.660298
          ],
          [
            -122.331326,
            47.660288
          ],
          [
            -122.331326,
            47.660283
          ],
          [
            -122.331332,
            47.66027
          ],
          [
            -122.331344,
            47.660258
          ],
          [
            -122.33136,
            47.66025
          ],
          [
            -122.331379,
            47.660246
          ],
          [
            -122.331388,
            47.660246
          ],
          [
            -122.331399,
            47.660247
          ],
          [
            -122.331418,
            47.660251
          ],
          [
            -122.331433,
            47.660259
          ],
          [
            -122.331444,
            47.66027
          ],
          [
            -122.33145,
            47.660283
          ],
          [
            -122.331449,
            47.660289
          ],
          [
            -122.331483,
            47.660289
          ],
          [
            -122.331886,
            47.660291
          ],
          [
            -122.332002,
            47.660291
          ]
        ],
        "duration_minutes": 16
      },
      "reasoning": "Transit strike has ended, but she prefers biking anyway. Early enough to enjoy the 68°F weather and partly cloudy skies. Generously budgeted for a relaxed pace home."
    },
    {
      "index": 7,
      "start_time": "2026-06-04T21:31:56.086Z",
      "end_time": "2026-06-04T22:12:32.608Z",
      "activity": "Change clothes, hydrate, review transit maps and sketch weekend kayaking route on Lake Union.",
      "activity_type": "leisure",
      "location_name": "Home (Wallingford)",
      "location": [
        -122.332,
        47.6605
      ],
      "travel_from_prev": null,
      "reasoning": "She's a transit-map collector and weekend kayaker; cool, organized downtime at home aligns with her personality. Low energy (45/100 yesterday) means she settles in early rather than going out."
    },
    {
      "index": 8,
      "start_time": "2026-06-04T22:12:32.608Z",
      "end_time": "2026-06-04T23:13:27.391Z",
      "activity": "Prepare and eat a light dinner at home; read or listen to music.",
      "activity_type": "meal",
      "location_name": "Home (Wallingford)",
      "location": [
        -122.332,
        47.6605
      ],
      "travel_from_prev": null,
      "reasoning": "Simple evening meal at home. Low energy and mild weather make this a cozy, introspective evening rather than a night out dancing or socializing."
    },
    {
      "index": 9,
      "start_time": "2026-06-04T23:13:27.391Z",
      "end_time": "2026-06-05T01:55:53.478Z",
      "activity": "Relax at home: organize bike maintenance notes, check emails, wind down for sleep.",
      "activity_type": "leisure",
      "location_name": "Home (Wallingford)",
      "location": [
        -122.332,
        47.6605
      ],
      "travel_from_prev": null,
      "reasoning": "Fiercely organized; uses evening to prep for tomorrow. Low energy from yesterday means an early wind-down. No late-night salsa or socializing today."
    },
    {
      "index": 10,
      "start_time": "2026-06-05T01:55:53.478Z",
      "end_time": "2026-06-05T13:00:00.000Z",
      "activity": "Sleep.",
      "activity_type": "sleep",
      "location_name": "Home (Wallingford)",
      "location": [
        -122.332,
        47.6605
      ],
      "travel_from_prev": null,
      "reasoning": "Early bedtime (6h 45m sleep) reflects low energy and a day spent mostly at work and home. She'll be fresh for Friday and ready for weekend cycling plans."
    }
  ],
  "diary": "Woke to that transit strike news and honestly felt a little smug—days like this remind me why I love the bike. The commute through Capitol Hill was perfect, 68 degrees and the light hitting just right. Shop was steady; tuned up three road bikes and helped a nervous woman pick her first gravel bike. She seemed relieved when I told her not to overthink it. Grabbed lunch at Pike, got some good greens, and the ride back felt effortless. Afternoon flew by with the usual mix of repairs and customers. By the time I headed home, the city felt oddly peaceful without all those buses rumbling around. Spent the evening sketching out a kayaking route for this weekend—Lake Union's been calling me. There's something about planning these little adventures that makes the regular work feel worthwhile.",
  "thought_process": "The strike actually worked in my favor today—no guilt about driving or taking transit, and I got to be exactly what I am: someone who moves through the city under their own power. That felt good, almost vindicated. The woman looking for her first gravel bike reminded me why I do this; there's real value in demystifying things for people. I deliberately left work a bit early because the afternoon had that restless energy, and I knew I'd be more present at home. Sketching that kayaking route was pure joy—mixing the practical (checking water conditions, marking launch points) with the dreamy part (imagining the paddle, the quiet). I'm in a good headspace, feeling capable and grounded.",
  "end_state": {
    "location": [
      -122.332,
      47.6605
    ],
    "energy": 45,
    "notes": ""
  },
  "world_event_prompt": "Mild, partly cloudy Thursday, high of 68F. Citywide transit strike: all Metro buses and Link Light Rail suspended until 4pm. Rideshare surge pricing in effect.",
  "generated_at": "2026-05-30T18:18:41.452Z",
  "stats": {
    "skeleton_attempts": 1,
    "repair_used": false,
    "geocode_misses": 0,
    "route_misses": 0,
    "overflow_fixed_by_shift": 4,
    "overflow_remaining": 0,
    "compressed_to_fit_day": true,
    "compressed_minutes_saved": 446,
    "sleep_beat_synthesized": false,
    "returned_home_before_sleep": true,
    "llm_ms": 5284,
    "mapbox_ms": 0,
    "total_ms": 19574
  },
  "_ok": true
}