{
  "sim_date": "2026-06-03",
  "day_number": 3,
  "agent_id": "2f46ce70-03ad-462e-afb0-157ed460b12b",
  "agent_name": "Isaac Yamamoto",
  "status": "ready",
  "beats": [
    {
      "index": 0,
      "start_time": "2026-06-03T14:15:00.000Z",
      "end_time": "2026-06-03T14:38:00.430Z",
      "activity": "Wake up, coffee, and check the weather forecast on the porch.",
      "activity_type": "home",
      "location_name": "Home (Ravenna)",
      "location": [
        -122.29749,
        47.67578
      ],
      "travel_from_prev": null,
      "reasoning": "Isaac wakes early as is his habit, eager to assess the hot, clear day ahead. The 91F forecast and smoke concerns mean he'll want to stay hydrated and plan indoor time strategically."
    },
    {
      "index": 1,
      "start_time": "2026-06-03T14:38:00.430Z",
      "end_time": "2026-06-03T15:01:00.860Z",
      "activity": "Bike commute from Ravenna to the shop, taking the scenic route along the Burke-Gilman Trail.",
      "activity_type": "commute",
      "location_name": "Burke-Gilman Trail to First Hill",
      "location": [
        -122.29749,
        47.67578
      ],
      "travel_from_prev": null,
      "reasoning": "Isaac always takes the scenic route; the trail is cooler than direct streets and avoids heat exposure early. He'll ride steady but not hard given the heat forecast."
    },
    {
      "index": 2,
      "start_time": "2026-06-03T15:25:00.860Z",
      "end_time": "2026-06-03T18:06:03.871Z",
      "activity": "Brake adjustments, derailleur tuning, and wheel truing at the shop. Stay hydrated between jobs.",
      "activity_type": "work",
      "location_name": "Bike Mechanic Shop (First Hill, Seattle)",
      "location": [
        -122.32083,
        47.614085
      ],
      "travel_from_prev": {
        "mode": "driving",
        "polyline": [
          [
            -122.297496,
            47.675781
          ],
          [
            -122.297706,
            47.67578
          ],
          [
            -122.298079,
            47.675781
          ],
          [
            -122.298219,
            47.675781
          ],
          [
            -122.298409,
            47.675781
          ],
          [
            -122.298414,
            47.675781
          ],
          [
            -122.298545,
            47.675781
          ],
          [
            -122.299336,
            47.675782
          ],
          [
            -122.299513,
            47.675782
          ],
          [
            -122.299612,
            47.675782
          ],
          [
            -122.299741,
            47.675783
          ],
          [
            -122.300071,
            47.675783
          ],
          [
            -122.300096,
            47.675783
          ],
          [
            -122.300139,
            47.675783
          ],
          [
            -122.300216,
            47.675783
          ],
          [
            -122.300231,
            47.675781
          ],
          [
            -122.300534,
            47.675783
          ],
          [
            -122.300664,
            47.675784
          ],
          [
            -122.300662,
            47.675695
          ],
          [
            -122.300653,
            47.673816
          ],
          [
            -122.300648,
            47.672444
          ],
          [
            -122.300647,
            47.672258
          ],
          [
            -122.300647,
            47.672235
          ],
          [
            -122.300647,
            47.672155
          ],
          [
            -122.300646,
            47.672085
          ],
          [
            -122.300644,
            47.671985
          ],
          [
            -122.300643,
            47.671876
          ],
          [
            -122.300627,
            47.670921
          ],
          [
            -122.300613,
            47.670068
          ],
          [
            -122.300612,
            47.669998
          ],
          [
            -122.300616,
            47.669042
          ],
          [
            -122.300618,
            47.668773
          ],
          [
            -122.300618,
            47.668724
          ],
          [
            -122.300618,
            47.668627
          ],
          [
            -122.300619,
            47.668534
          ],
          [
            -122.300618,
            47.668437
          ],
          [
            -122.300618,
            47.668421
          ],
          [
            -122.300618,
            47.668381
          ],
          [
            -122.300618,
            47.668275
          ],
          [
            -122.300617,
            47.668162
          ],
          [
            -122.300617,
            47.668149
          ],
          [
            -122.300617,
            47.668071
          ],
          [
            -122.300617,
            47.667991
          ],
          [
            -122.30062,
            47.667916
          ],
          [
            -122.300628,
            47.667755
          ],
          [
            -122.300626,
            47.66754
          ],
          [
            -122.300625,
            47.667341
          ],
          [
            -122.300621,
            47.666992
          ],
          [
            -122.300622,
            47.666842
          ],
          [
            -122.300621,
            47.666709
          ],
          [
            -122.300608,
            47.666547
          ],
          [
            -122.300607,
            47.666502
          ],
          [
            -122.300606,
            47.666389
          ],
          [
            -122.300606,
            47.666292
          ],
          [
            -122.300606,
            47.666179
          ],
          [
            -122.300611,
            47.66606
          ],
          [
            -122.300612,
            47.666001
          ],
          [
            -122.300616,
            47.665909
          ],
          [
            -122.300619,
            47.665889
          ],
          [
            -122.300635,
            47.66574
          ],
          [
            -122.300646,
            47.665668
          ],
          [
            -122.300676,
            47.665547
          ],
          [
            -122.300691,
            47.665454
          ],
          [
            -122.300709,
            47.665385
          ],
          [
            -122.300824,
            47.664945
          ],
          [
            -122.300829,
            47.664925
          ],
          [
            -122.30085,
            47.664848
          ],
          [
            -122.300862,
            47.664801
          ],
          [
            -122.300865,
            47.664787
          ],
          [
            -122.300874,
            47.664759
          ],
          [
            -122.300893,
            47.664621
          ],
          [
            -122.300898,
            47.664549
          ],
          [
            -122.300901,
            47.664504
          ],
          [
            -122.300903,
            47.664466
          ],
          [
            -122.300906,
            47.664415
          ],
          [
            -122.300905,
            47.664289
          ],
          [
            -122.300904,
            47.664096
          ],
          [
            -122.300902,
            47.663779
          ],
          [
            -122.300902,
            47.663699
          ],
          [
            -122.300901,
            47.663639
          ],
          [
            -122.300901,
            47.663566
          ],
          [
            -122.3009,
            47.663381
          ],
          [
            -122.300899,
            47.663292
          ],
          [
            -122.300899,
            47.663204
          ],
          [
            -122.300899,
            47.663181
          ],
          [
            -122.300899,
            47.663153
          ],
          [
            -122.300897,
            47.662856
          ],
          [
            -122.300895,
            47.662589
          ],
          [
            -122.300895,
            47.662516
          ],
          [
            -122.300894,
            47.662447
          ],
          [
            -122.300892,
            47.662058
          ],
          [
            -122.30089,
            47.661812
          ],
          [
            -122.300892,
            47.661383
          ],
          [
            -122.300893,
            47.661332
          ],
          [
            -122.300899,
            47.661095
          ],
          [
            -122.300903,
            47.660947
          ],
          [
            -122.300906,
            47.660625
          ],
          [
            -122.300912,
            47.660497
          ],
          [
            -122.300919,
            47.660359
          ],
          [
            -122.300923,
            47.660342
          ],
          [
            -122.300947,
            47.660224
          ],
          [
            -122.301032,
            47.660074
          ],
          [
            -122.301085,
            47.659631
          ],
          [
            -122.301089,
            47.659598
          ],
          [
            -122.301159,
            47.659166
          ],
          [
            -122.301371,
            47.658688
          ],
          [
            -122.301425,
            47.658325
          ],
          [
            -122.301482,
            47.65813
          ],
          [
            -122.301533,
            47.657954
          ],
          [
            -122.301842,
            47.656893
          ],
          [
            -122.301999,
            47.656399
          ],
          [
            -122.302067,
            47.656182
          ],
          [
            -122.302087,
            47.65612
          ],
          [
            -122.302121,
            47.656011
          ],
          [
            -122.302229,
            47.655813
          ],
          [
            -122.302513,
            47.654863
          ],
          [
            -122.30272,
            47.654127
          ],
          [
            -122.30298,
            47.653273
          ],
          [
            -122.303039,
            47.653079
          ],
          [
            -122.303053,
            47.653035
          ],
          [
            -122.303091,
            47.652915
          ],
          [
            -122.303174,
            47.652654
          ],
          [
            -122.303271,
            47.652418
          ],
          [
            -122.303318,
            47.652138
          ],
          [
            -122.303489,
            47.651803
          ],
          [
            -122.303619,
            47.651562
          ],
          [
            -122.303886,
            47.651066
          ],
          [
            -122.303961,
            47.65094
          ],
          [
            -122.30399,
            47.650889
          ],
          [
            -122.304126,
            47.650645
          ],
          [
            -122.304178,
            47.650556
          ],
          [
            -122.304241,
            47.650406
          ],
          [
            -122.304347,
            47.650155
          ],
          [
            -122.304409,
            47.649978
          ],
          [
            -122.304476,
            47.64976
          ],
          [
            -122.304504,
            47.649661
          ],
          [
            -122.304506,
            47.649653
          ],
          [
            -122.304545,
            47.649514
          ],
          [
            -122.304559,
            47.649351
          ],
          [
            -122.304559,
            47.649349
          ],
          [
            -122.30456,
            47.649342
          ],
          [
            -122.304572,
            47.649204
          ],
          [
            -122.304583,
            47.649019
          ],
          [
            -122.304593,
            47.648792
          ],
          [
            -122.304604,
            47.648538
          ],
          [
            -122.304611,
            47.648244
          ],
          [
            -122.304615,
            47.64803
          ],
          [
            -122.304617,
            47.647824
          ],
          [
            -122.304616,
            47.647819
          ],
          [
            -122.304614,
            47.64772
          ],
          [
            -122.304614,
            47.647689
          ],
          [
            -122.304613,
            47.64768
          ],
          [
            -122.304614,
            47.647577
          ],
          [
            -122.304616,
            47.647466
          ],
          [
            -122.304619,
            47.647293
          ],
          [
            -122.304619,
            47.647273
          ],
          [
            -122.304621,
            47.647122
          ],
          [
            -122.304626,
            47.646975
          ],
          [
            -122.304624,
            47.646952
          ],
          [
            -122.304624,
            47.646908
          ],
          [
            -122.304624,
            47.646904
          ],
          [
            -122.304625,
            47.64686
          ],
          [
            -122.304626,
            47.646772
          ],
          [
            -122.304626,
            47.646769
          ],
          [
            -122.304669,
            47.646667
          ],
          [
            -122.304683,
            47.646559
          ],
          [
            -122.304685,
            47.646543
          ],
          [
            -122.304701,
            47.646414
          ],
          [
            -122.304707,
            47.646328
          ],
          [
            -122.304711,
            47.646274
          ],
          [
            -122.304712,
            47.646155
          ],
          [
            -122.304714,
            47.645936
          ],
          [
            -122.304756,
            47.645557
          ],
          [
            -122.304763,
            47.645271
          ],
          [
            -122.304754,
            47.645131
          ],
          [
            -122.304717,
            47.644958
          ],
          [
            -122.304659,
            47.644803
          ],
          [
            -122.304549,
            47.644617
          ],
          [
            -122.304495,
            47.644525
          ],
          [
            -122.304451,
            47.644452
          ],
          [
            -122.304385,
            47.644343
          ],
          [
            -122.304368,
            47.644314
          ],
          [
            -122.304297,
            47.644196
          ],
          [
            -122.304219,
            47.644066
          ],
          [
            -122.304143,
            47.643951
          ],
          [
            -122.304104,
            47.643896
          ],
          [
            -122.304098,
            47.643889
          ],
          [
            -122.304016,
            47.643788
          ],
          [
            -122.30397,
            47.643736
          ],
          [
            -122.3039,
            47.64366
          ],
          [
            -122.303794,
            47.643547
          ],
          [
            -122.303647,
            47.643443
          ],
          [
            -122.303636,
            47.643437
          ],
          [
            -122.303628,
            47.643433
          ],
          [
            -122.303479,
            47.643352
          ],
          [
            -122.303349,
            47.643306
          ],
          [
            -122.303265,
            47.643249
          ],
          [
            -122.303126,
            47.643152
          ],
          [
            -122.302986,
            47.643056
          ],
          [
            -122.302872,
            47.643026
          ],
          [
            -122.30283,
            47.642995
          ],
          [
            -122.302645,
            47.64286
          ],
          [
            -122.302319,
            47.642621
          ],
          [
            -122.302252,
            47.64257
          ],
          [
            -122.302195,
            47.642514
          ],
          [
            -122.302148,
            47.642454
          ],
          [
            -122.302114,
            47.642396
          ],
          [
            -122.302091,
            47.642336
          ],
          [
            -122.302077,
            47.642275
          ],
          [
            -122.302072,
            47.642213
          ],
          [
            -122.302076,
            47.641766
          ],
          [
            -122.302077,
            47.641715
          ],
          [
            -122.302077,
            47.641657
          ],
          [
            -122.30208,
            47.641062
          ],
          [
            -122.302081,
            47.640983
          ],
          [
            -122.302081,
            47.640937
          ],
          [
            -122.302083,
            47.640727
          ],
          [
            -122.302084,
            47.640658
          ],
          [
            -122.302086,
            47.640333
          ],
          [
            -122.302088,
            47.64026
          ],
          [
            -122.302087,
            47.640195
          ],
          [
            -122.302087,
            47.640134
          ],
          [
            -122.302087,
            47.639967
          ],
          [
            -122.302087,
            47.639645
          ],
          [
            -122.302081,
            47.639599
          ],
          [
            -122.302068,
            47.639528
          ],
          [
            -122.302052,
            47.639465
          ],
          [
            -122.302049,
            47.639452
          ],
          [
            -122.301925,
            47.639117
          ],
          [
            -122.301817,
            47.638777
          ],
          [
            -122.301797,
            47.638714
          ],
          [
            -122.301663,
            47.638324
          ],
          [
            -122.301588,
            47.638085
          ],
          [
            -122.301556,
            47.637985
          ],
          [
            -122.301553,
            47.637972
          ],
          [
            -122.301542,
            47.637924
          ],
          [
            -122.301537,
            47.637891
          ],
          [
            -122.301535,
            47.637864
          ],
          [
            -122.301533,
            47.637821
          ],
          [
            -122.301535,
            47.63769
          ],
          [
            -122.301546,
            47.637071
          ],
          [
            -122.30156,
            47.636227
          ],
          [
            -122.301573,
            47.635409
          ],
          [
            -122.301574,
            47.635347
          ],
          [
            -122.301576,
            47.635262
          ],
          [
            -122.301576,
            47.635254
          ],
          [
            -122.301577,
            47.635207
          ],
          [
            -122.301577,
            47.635187
          ],
          [
            -122.30158,
            47.635072
          ],
          [
            -122.301581,
            47.635043
          ],
          [
            -122.301584,
            47.634918
          ],
          [
            -122.301586,
            47.634798
          ],
          [
            -122.301593,
            47.63458
          ],
          [
            -122.301594,
            47.63437
          ],
          [
            -122.301598,
            47.634146
          ],
          [
            -122.301609,
            47.633613
          ],
          [
            -122.301614,
            47.633361
          ],
          [
            -122.301624,
            47.632816
          ],
          [
            -122.301628,
            47.632563
          ],
          [
            -122.301631,
            47.632431
          ],
          [
            -122.301632,
            47.632348
          ],
          [
            -122.301632,
            47.632327
          ],
          [
            -122.301633,
            47.632284
          ],
          [
            -122.301635,
            47.63223
          ],
          [
            -122.301638,
            47.63207
          ],
          [
            -122.301651,
            47.631289
          ],
          [
            -122.301668,
            47.630268
          ],
          [
            -122.301672,
            47.63001
          ],
          [
            -122.301681,
            47.629507
          ],
          [
            -122.301683,
            47.629359
          ],
          [
            -122.301685,
            47.629269
          ],
          [
            -122.301686,
            47.629196
          ],
          [
            -122.30169,
            47.629021
          ],
          [
            -122.3017,
            47.628416
          ],
          [
            -122.301707,
            47.628311
          ],
          [
            -122.301726,
            47.628239
          ],
          [
            -122.301749,
            47.628181
          ],
          [
            -122.301777,
            47.62813
          ],
          [
            -122.3018,
            47.628096
          ],
          [
            -122.301834,
            47.628052
          ],
          [
            -122.301965,
            47.627877
          ],
          [
            -122.30207,
            47.627824
          ],
          [
            -122.302257,
            47.62761
          ],
          [
            -122.30232,
            47.627531
          ],
          [
            -122.302363,
            47.627472
          ],
          [
            -122.302396,
            47.627404
          ],
          [
            -122.302418,
            47.627355
          ],
          [
            -122.302393,
            47.627254
          ],
          [
            -122.302396,
            47.627065
          ],
          [
            -122.302399,
            47.626893
          ],
          [
            -122.3024,
            47.626822
          ],
          [
            -122.302401,
            47.626756
          ],
          [
            -122.302402,
            47.626694
          ],
          [
            -122.302404,
            47.626582
          ],
          [
            -122.302408,
            47.626311
          ],
          [
            -122.302411,
            47.626014
          ],
          [
            -122.302412,
            47.625948
          ],
          [
            -122.302413,
            47.625886
          ],
          [
            -122.30242,
            47.625582
          ],
          [
            -122.302424,
            47.625336
          ],
          [
            -122.302426,
            47.625266
          ],
          [
            -122.302427,
            47.625202
          ],
          [
            -122.302428,
            47.625137
          ],
          [
            -122.30243,
            47.624961
          ],
          [
            -122.302438,
            47.624466
          ],
          [
            -122.302439,
            47.624398
          ],
          [
            -122.30244,
            47.624321
          ],
          [
            -122.302449,
            47.623788
          ],
          [
            -122.302455,
            47.623412
          ],
          [
            -122.302458,
            47.623247
          ],
          [
            -122.302459,
            47.623172
          ],
          [
            -122.30246,
            47.623115
          ],
          [
            -122.302463,
            47.622984
          ],
          [
            -122.302468,
            47.622731
          ],
          [
            -122.30247,
            47.622662
          ],
          [
            -122.302471,
            47.622575
          ],
          [
            -122.30248,
            47.622159
          ],
          [
            -122.302494,
            47.621451
          ],
          [
            -122.302496,
            47.621377
          ],
          [
            -122.302497,
            47.621315
          ],
          [
            -122.302502,
            47.621132
          ],
          [
            -122.302512,
            47.620676
          ],
          [
            -122.302514,
            47.620603
          ],
          [
            -122.302515,
            47.620528
          ],
          [
            -122.302519,
            47.620314
          ],
          [
            -122.302522,
            47.620215
          ],
          [
            -122.302523,
            47.620131
          ],
          [
            -122.302529,
            47.619929
          ],
          [
            -122.302532,
            47.619802
          ],
          [
            -122.302541,
            47.619396
          ],
          [
            -122.302541,
            47.619394
          ],
          [
            -122.302542,
            47.61934
          ],
          [
            -122.302541,
            47.619308
          ],
          [
            -122.302545,
            47.619184
          ],
          [
            -122.302669,
            47.6191
          ],
          [
            -122.302915,
            47.618933
          ],
          [
            -122.303083,
            47.618821
          ],
          [
            -122.303138,
            47.618785
          ],
          [
            -122.303649,
            47.618445
          ],
          [
            -122.303784,
            47.618357
          ],
          [
            -122.303953,
            47.618246
          ],
          [
            -122.304094,
            47.618153
          ],
          [
            -122.304176,
            47.618105
          ],
          [
            -122.30428,
            47.618063
          ],
          [
            -122.304668,
            47.617898
          ],
          [
            -122.304932,
            47.617787
          ],
          [
            -122.305324,
            47.617622
          ],
          [
            -122.306034,
            47.617318
          ],
          [
            -122.306157,
            47.617266
          ],
          [
            -122.306249,
            47.617227
          ],
          [
            -122.306625,
            47.617072
          ],
          [
            -122.306632,
            47.617069
          ],
          [
            -122.306864,
            47.616973
          ],
          [
            -122.306875,
            47.616969
          ],
          [
            -122.307325,
            47.616782
          ],
          [
            -122.307419,
            47.616743
          ],
          [
            -122.307557,
            47.616684
          ],
          [
            -122.308756,
            47.616175
          ],
          [
            -122.308864,
            47.616128
          ],
          [
            -122.308954,
            47.61609
          ],
          [
            -122.309131,
            47.616016
          ],
          [
            -122.309934,
            47.61568
          ],
          [
            -122.31006,
            47.615627
          ],
          [
            -122.310145,
            47.615592
          ],
          [
            -122.310286,
            47.615534
          ],
          [
            -122.310587,
            47.615411
          ],
          [
            -122.310983,
            47.615248
          ],
          [
            -122.31115,
            47.615179
          ],
          [
            -122.311251,
            47.615138
          ],
          [
            -122.311414,
            47.615068
          ],
          [
            -122.311483,
            47.615038
          ],
          [
            -122.311937,
            47.614851
          ],
          [
            -122.311951,
            47.614845
          ],
          [
            -122.312671,
            47.614547
          ],
          [
            -122.312777,
            47.614503
          ],
          [
            -122.312796,
            47.614495
          ],
          [
            -122.312846,
            47.614474
          ],
          [
            -122.313457,
            47.614219
          ],
          [
            -122.313488,
            47.614207
          ],
          [
            -122.313566,
            47.614174
          ],
          [
            -122.313658,
            47.614135
          ],
          [
            -122.313682,
            47.614125
          ],
          [
            -122.313754,
            47.614095
          ],
          [
            -122.313805,
            47.61415
          ],
          [
            -122.313817,
            47.614162
          ],
          [
            -122.313842,
            47.614175
          ],
          [
            -122.313878,
            47.614178
          ],
          [
            -122.314127,
            47.614177
          ],
          [
            -122.314152,
            47.614176
          ],
          [
            -122.314237,
            47.61413
          ],
          [
            -122.314376,
            47.614129
          ],
          [
            -122.314841,
            47.614133
          ],
          [
            -122.31503,
            47.614129
          ],
          [
            -122.315402,
            47.614118
          ],
          [
            -122.315441,
            47.614118
          ],
          [
            -122.315543,
            47.614118
          ],
          [
            -122.315548,
            47.614118
          ],
          [
            -122.315643,
            47.614118
          ],
          [
            -122.315687,
            47.614117
          ],
          [
            -122.316704,
            47.614103
          ],
          [
            -122.316729,
            47.614103
          ],
          [
            -122.316818,
            47.614103
          ],
          [
            -122.317003,
            47.614102
          ],
          [
            -122.317192,
            47.614102
          ],
          [
            -122.318027,
            47.6141
          ],
          [
            -122.318145,
            47.6141
          ],
          [
            -122.31828,
            47.614099
          ],
          [
            -122.318927,
            47.614098
          ],
          [
            -122.31932,
            47.614096
          ],
          [
            -122.319455,
            47.614096
          ],
          [
            -122.319583,
            47.614095
          ],
          [
            -122.320393,
            47.614092
          ],
          [
            -122.320616,
            47.614091
          ],
          [
            -122.320716,
            47.614091
          ],
          [
            -122.320782,
            47.61409
          ],
          [
            -122.320828,
            47.61409
          ]
        ],
        "duration_minutes": 24
      },
      "reasoning": "Morning work block before the heat peaks. Isaac focuses on precision tasks that don't require outdoor exposure. He'll drink water frequently given the smoke and heat."
    },
    {
      "index": 3,
      "start_time": "2026-06-03T18:06:03.871Z",
      "end_time": "2026-06-03T18:38:55.914Z",
      "activity": "Lunch at Victrola Coffee, ordering the usual soup and iced drink to stay cool.",
      "activity_type": "meal",
      "location_name": "Victrola Coffee (First Hill, Seattle)",
      "location": [
        -122.32083,
        47.614085
      ],
      "travel_from_prev": null,
      "reasoning": "Indoor meal during peak heat. The barista knows his order, and the air conditioning is a practical choice on a 91F day with smoke in the air."
    },
    {
      "index": 4,
      "start_time": "2026-06-03T18:38:55.914Z",
      "end_time": "2026-06-03T19:05:13.548Z",
      "activity": "Walk back to the shop through the heat, taking shade where possible.",
      "activity_type": "commute",
      "location_name": "Bike Mechanic Shop (First Hill, Seattle)",
      "location": [
        -122.32083,
        47.614085
      ],
      "travel_from_prev": null,
      "reasoning": "Short walk back to the shop; he'll move slowly and hydrate to avoid heat stress during the hottest part of the afternoon."
    },
    {
      "index": 5,
      "start_time": "2026-06-03T19:05:13.548Z",
      "end_time": "2026-06-03T21:23:16.129Z",
      "activity": "Afternoon work: customer bikes, inventory checks, and light admin in the cooler shop interior.",
      "activity_type": "work",
      "location_name": "Bike Mechanic Shop (First Hill, Seattle)",
      "location": [
        -122.32083,
        47.614085
      ],
      "travel_from_prev": null,
      "reasoning": "Isaac stays indoors during peak heat and smoke hours. Focus on repetitive, meditative work—the kind that doesn't require leaving the shop's air conditioning."
    },
    {
      "index": 6,
      "start_time": "2026-06-03T21:42:16.129Z",
      "end_time": "2026-06-03T22:08:33.763Z",
      "activity": "Easy bike ride from First Hill to Gas Works Park, taking back streets and staying in shade.",
      "activity_type": "commute",
      "location_name": "Gas Works Park (Wallingford, Seattle)",
      "location": [
        -122.3344,
        47.6457
      ],
      "travel_from_prev": {
        "mode": "driving",
        "polyline": [
          [
            -122.320828,
            47.61409
          ],
          [
            -122.320871,
            47.61409
          ],
          [
            -122.320978,
            47.614089
          ],
          [
            -122.321457,
            47.614085
          ],
          [
            -122.32202,
            47.614082
          ],
          [
            -122.322128,
            47.614081
          ],
          [
            -122.322222,
            47.614081
          ],
          [
            -122.323261,
            47.614076
          ],
          [
            -122.323327,
            47.614084
          ],
          [
            -122.323411,
            47.614094
          ],
          [
            -122.323524,
            47.614106
          ],
          [
            -122.324367,
            47.614105
          ],
          [
            -122.32447,
            47.614105
          ],
          [
            -122.324579,
            47.614104
          ],
          [
            -122.325413,
            47.614103
          ],
          [
            -122.325517,
            47.614103
          ],
          [
            -122.325633,
            47.614103
          ],
          [
            -122.325848,
            47.614103
          ],
          [
            -122.32618,
            47.614103
          ],
          [
            -122.326203,
            47.614103
          ],
          [
            -122.326708,
            47.614102
          ],
          [
            -122.326821,
            47.614102
          ],
          [
            -122.32682,
            47.614148
          ],
          [
            -122.326819,
            47.614206
          ],
          [
            -122.326805,
            47.615107
          ],
          [
            -122.326803,
            47.615224
          ],
          [
            -122.326939,
            47.615224
          ],
          [
            -122.32727,
            47.615224
          ],
          [
            -122.32779,
            47.615225
          ],
          [
            -122.327899,
            47.615225
          ],
          [
            -122.327938,
            47.615222
          ],
          [
            -122.327977,
            47.615216
          ],
          [
            -122.328014,
            47.615209
          ],
          [
            -122.328041,
            47.615201
          ],
          [
            -122.328086,
            47.615187
          ],
          [
            -122.328152,
            47.615161
          ],
          [
            -122.328696,
            47.614935
          ],
          [
            -122.328722,
            47.614924
          ],
          [
            -122.328927,
            47.614836
          ],
          [
            -122.32894,
            47.61483
          ],
          [
            -122.329702,
            47.614502
          ],
          [
            -122.329806,
            47.614457
          ],
          [
            -122.32987,
            47.614528
          ],
          [
            -122.330149,
            47.614829
          ],
          [
            -122.330289,
            47.614978
          ],
          [
            -122.330333,
            47.615028
          ],
          [
            -122.330487,
            47.615195
          ],
          [
            -122.330664,
            47.615389
          ],
          [
            -122.330729,
            47.615459
          ],
          [
            -122.330789,
            47.615523
          ],
          [
            -122.331073,
            47.61582
          ],
          [
            -122.331169,
            47.61592
          ],
          [
            -122.331366,
            47.616127
          ],
          [
            -122.331421,
            47.616184
          ],
          [
            -122.331502,
            47.616233
          ],
          [
            -122.331809,
            47.616417
          ],
          [
            -122.331975,
            47.616515
          ],
          [
            -122.331998,
            47.61653
          ],
          [
            -122.332316,
            47.616721
          ],
          [
            -122.332609,
            47.616896
          ],
          [
            -122.332705,
            47.616953
          ],
          [
            -122.332826,
            47.617025
          ],
          [
            -122.332946,
            47.617095
          ],
          [
            -122.333062,
            47.617164
          ],
          [
            -122.333445,
            47.617389
          ],
          [
            -122.333629,
            47.617497
          ],
          [
            -122.333718,
            47.617549
          ],
          [
            -122.33392,
            47.617654
          ],
          [
            -122.333917,
            47.617677
          ],
          [
            -122.333941,
            47.617692
          ],
          [
            -122.334005,
            47.61773
          ],
          [
            -122.334075,
            47.617773
          ],
          [
            -122.334117,
            47.617798
          ],
          [
            -122.334153,
            47.617804
          ],
          [
            -122.33416,
            47.617808
          ],
          [
            -122.334293,
            47.617878
          ],
          [
            -122.334291,
            47.618095
          ],
          [
            -122.334297,
            47.618362
          ],
          [
            -122.334297,
            47.618426
          ],
          [
            -122.334299,
            47.618528
          ],
          [
            -122.334505,
            47.618529
          ],
          [
            -122.334594,
            47.618529
          ],
          [
            -122.334835,
            47.618529
          ],
          [
            -122.334873,
            47.618529
          ],
          [
            -122.335075,
            47.61853
          ],
          [
            -122.335284,
            47.618531
          ],
          [
            -122.335888,
            47.618532
          ],
          [
            -122.336395,
            47.618534
          ],
          [
            -122.336466,
            47.618562
          ],
          [
            -122.337207,
            47.618564
          ],
          [
            -122.337302,
            47.618564
          ],
          [
            -122.337562,
            47.618563
          ],
          [
            -122.337663,
            47.618536
          ],
          [
            -122.337838,
            47.618538
          ],
          [
            -122.337995,
            47.618539
          ],
          [
            -122.338315,
            47.61854
          ],
          [
            -122.338408,
            47.618541
          ],
          [
            -122.33849,
            47.618541
          ],
          [
            -122.33859,
            47.618541
          ],
          [
            -122.33866,
            47.618541
          ],
          [
            -122.338991,
            47.618543
          ],
          [
            -122.339148,
            47.618543
          ],
          [
            -122.33972,
            47.618545
          ],
          [
            -122.339861,
            47.618545
          ],
          [
            -122.339961,
            47.618546
          ],
          [
            -122.339972,
            47.618546
          ],
          [
            -122.340041,
            47.618547
          ],
          [
            -122.340341,
            47.618549
          ],
          [
            -122.340458,
            47.618578
          ],
          [
            -122.341407,
            47.618587
          ],
          [
            -122.341569,
            47.618555
          ],
          [
            -122.341685,
            47.618555
          ],
          [
            -122.34211,
            47.618553
          ],
          [
            -122.342158,
            47.618553
          ],
          [
            -122.342225,
            47.618553
          ],
          [
            -122.342255,
            47.618553
          ],
          [
            -122.342316,
            47.618554
          ],
          [
            -122.342396,
            47.618554
          ],
          [
            -122.342629,
            47.618556
          ],
          [
            -122.342758,
            47.618558
          ],
          [
            -122.343218,
            47.618563
          ],
          [
            -122.343284,
            47.618563
          ],
          [
            -122.343411,
            47.618563
          ],
          [
            -122.343586,
            47.618563
          ],
          [
            -122.343564,
            47.618639
          ],
          [
            -122.343563,
            47.618657
          ],
          [
            -122.34356,
            47.618709
          ],
          [
            -122.343564,
            47.61882
          ],
          [
            -122.343576,
            47.619204
          ],
          [
            -122.34358,
            47.61936
          ],
          [
            -122.343587,
            47.619624
          ],
          [
            -122.34359,
            47.61973
          ],
          [
            -122.343592,
            47.619834
          ],
          [
            -122.343599,
            47.620207
          ],
          [
            -122.343605,
            47.620516
          ],
          [
            -122.343656,
            47.6208
          ],
          [
            -122.343656,
            47.620853
          ],
          [
            -122.343656,
            47.62089
          ],
          [
            -122.343656,
            47.620909
          ],
          [
            -122.343656,
            47.620926
          ],
          [
            -122.343656,
            47.620969
          ],
          [
            -122.343655,
            47.62102
          ],
          [
            -122.343655,
            47.621103
          ],
          [
            -122.343655,
            47.621183
          ],
          [
            -122.343655,
            47.621266
          ],
          [
            -122.343655,
            47.621345
          ],
          [
            -122.343655,
            47.621431
          ],
          [
            -122.343654,
            47.621511
          ],
          [
            -122.343654,
            47.621592
          ],
          [
            -122.343654,
            47.621674
          ],
          [
            -122.343654,
            47.621756
          ],
          [
            -122.343654,
            47.621768
          ],
          [
            -122.343655,
            47.621784
          ],
          [
            -122.343653,
            47.621969
          ],
          [
            -122.343652,
            47.622066
          ],
          [
            -122.343652,
            47.622071
          ],
          [
            -122.343651,
            47.622167
          ],
          [
            -122.343658,
            47.622209
          ],
          [
            -122.343676,
            47.622284
          ],
          [
            -122.343695,
            47.622345
          ],
          [
            -122.34372,
            47.622411
          ],
          [
            -122.343759,
            47.622506
          ],
          [
            -122.343832,
            47.622643
          ],
          [
            -122.343888,
            47.622737
          ],
          [
            -122.34393,
            47.622834
          ],
          [
            -122.343955,
            47.622934
          ],
          [
            -122.343963,
            47.623035
          ],
          [
            -122.343957,
            47.623137
          ],
          [
            -122.343946,
            47.623197
          ],
          [
            -122.343931,
            47.623256
          ],
          [
            -122.343913,
            47.623314
          ],
          [
            -122.34388,
            47.623394
          ],
          [
            -122.34381,
            47.623552
          ],
          [
            -122.343771,
            47.623652
          ],
          [
            -122.343712,
            47.623835
          ],
          [
            -122.34368,
            47.623968
          ],
          [
            -122.343654,
            47.624102
          ],
          [
            -122.343637,
            47.624236
          ],
          [
            -122.343626,
            47.624367
          ],
          [
            -122.343614,
            47.624646
          ],
          [
            -122.343614,
            47.624656
          ],
          [
            -122.343611,
            47.624727
          ],
          [
            -122.343597,
            47.624791
          ],
          [
            -122.343596,
            47.624967
          ],
          [
            -122.343596,
            47.625114
          ],
          [
            -122.343585,
            47.625408
          ],
          [
            -122.343561,
            47.625922
          ],
          [
            -122.343553,
            47.626064
          ],
          [
            -122.343536,
            47.626263
          ],
          [
            -122.343519,
            47.626463
          ],
          [
            -122.34349,
            47.627146
          ],
          [
            -122.343471,
            47.628101
          ],
          [
            -122.343455,
            47.628905
          ],
          [
            -122.343448,
            47.629247
          ],
          [
            -122.343447,
            47.629388
          ],
          [
            -122.343443,
            47.629734
          ],
          [
            -122.343442,
            47.629825
          ],
          [
            -122.343429,
            47.630609
          ],
          [
            -122.343411,
            47.632262
          ],
          [
            -122.34341,
            47.632348
          ],
          [
            -122.343406,
            47.632558
          ],
          [
            -122.343395,
            47.63339
          ],
          [
            -122.343384,
            47.634256
          ],
          [
            -122.343383,
            47.634625
          ],
          [
            -122.343381,
            47.635305
          ],
          [
            -122.34338,
            47.635558
          ],
          [
            -122.343419,
            47.635891
          ],
          [
            -122.343462,
            47.636066
          ],
          [
            -122.343515,
            47.636202
          ],
          [
            -122.343727,
            47.63661
          ],
          [
            -122.344252,
            47.637353
          ],
          [
            -122.344304,
            47.637433
          ],
          [
            -122.344323,
            47.637461
          ],
          [
            -122.345209,
            47.638746
          ],
          [
            -122.345246,
            47.638799
          ],
          [
            -122.345393,
            47.639022
          ],
          [
            -122.345452,
            47.639111
          ],
          [
            -122.345472,
            47.639147
          ],
          [
            -122.345753,
            47.639608
          ],
          [
            -122.34578,
            47.639661
          ],
          [
            -122.346158,
            47.640383
          ],
          [
            -122.346319,
            47.640776
          ],
          [
            -122.34635,
            47.64086
          ],
          [
            -122.346756,
            47.641966
          ],
          [
            -122.346833,
            47.642177
          ],
          [
            -122.346923,
            47.642447
          ],
          [
            -122.347034,
            47.642699
          ],
          [
            -122.34708,
            47.642857
          ],
          [
            -122.347134,
            47.643006
          ],
          [
            -122.347212,
            47.643161
          ],
          [
            -122.347236,
            47.643301
          ],
          [
            -122.347258,
            47.643447
          ],
          [
            -122.347276,
            47.643594
          ],
          [
            -122.34729,
            47.64374
          ],
          [
            -122.347299,
            47.643887
          ],
          [
            -122.3473,
            47.649062
          ],
          [
            -122.347303,
            47.649304
          ],
          [
            -122.347322,
            47.651198
          ],
          [
            -122.347266,
            47.651365
          ],
          [
            -122.34718,
            47.651555
          ],
          [
            -122.347121,
            47.651649
          ],
          [
            -122.34706,
            47.651753
          ],
          [
            -122.347006,
            47.651831
          ],
          [
            -122.346944,
            47.651904
          ],
          [
            -122.346867,
            47.651995
          ],
          [
            -122.346759,
            47.652122
          ],
          [
            -122.346673,
            47.652204
          ],
          [
            -122.346592,
            47.652277
          ],
          [
            -122.346496,
            47.65235
          ],
          [
            -122.346417,
            47.652397
          ],
          [
            -122.346309,
            47.652461
          ],
          [
            -122.346149,
            47.652553
          ],
          [
            -122.346094,
            47.652585
          ],
          [
            -122.345827,
            47.652736
          ],
          [
            -122.345699,
            47.652735
          ],
          [
            -122.345319,
            47.652733
          ],
          [
            -122.345084,
            47.65273
          ],
          [
            -122.3448,
            47.652727
          ],
          [
            -122.344741,
            47.652727
          ],
          [
            -122.344684,
            47.652726
          ],
          [
            -122.34411,
            47.652723
          ],
          [
            -122.343996,
            47.652722
          ],
          [
            -122.343901,
            47.652722
          ],
          [
            -122.34343,
            47.652718
          ],
          [
            -122.342741,
            47.652713
          ],
          [
            -122.342576,
            47.652711
          ],
          [
            -122.342579,
            47.652629
          ],
          [
            -122.342581,
            47.6526
          ],
          [
            -122.342581,
            47.652598
          ],
          [
            -122.342589,
            47.652441
          ],
          [
            -122.342605,
            47.652129
          ],
          [
            -122.342668,
            47.650866
          ],
          [
            -122.342679,
            47.650641
          ],
          [
            -122.342684,
            47.650529
          ],
          [
            -122.342722,
            47.64979
          ],
          [
            -122.342724,
            47.649753
          ],
          [
            -122.342726,
            47.649712
          ],
          [
            -122.342733,
            47.649523
          ],
          [
            -122.342738,
            47.649443
          ],
          [
            -122.342742,
            47.64935
          ],
          [
            -122.342749,
            47.649224
          ],
          [
            -122.342763,
            47.648972
          ],
          [
            -122.342773,
            47.648788
          ],
          [
            -122.342782,
            47.648635
          ],
          [
            -122.342788,
            47.648526
          ],
          [
            -122.342793,
            47.648433
          ],
          [
            -122.342794,
            47.648423
          ],
          [
            -122.342794,
            47.64834
          ],
          [
            -122.342796,
            47.648269
          ],
          [
            -122.342791,
            47.648246
          ],
          [
            -122.342781,
            47.648224
          ],
          [
            -122.342767,
            47.648202
          ],
          [
            -122.342749,
            47.648182
          ],
          [
            -122.34271,
            47.648154
          ],
          [
            -122.342663,
            47.648133
          ],
          [
            -122.342611,
            47.648119
          ],
          [
            -122.34227,
            47.648063
          ],
          [
            -122.342068,
            47.64803
          ],
          [
            -122.341238,
            47.647894
          ],
          [
            -122.340965,
            47.647848
          ],
          [
            -122.340806,
            47.647816
          ],
          [
            -122.340649,
            47.647778
          ],
          [
            -122.340495,
            47.647736
          ],
          [
            -122.340344,
            47.64769
          ],
          [
            -122.340196,
            47.647639
          ],
          [
            -122.339943,
            47.647542
          ],
          [
            -122.339648,
            47.647405
          ],
          [
            -122.339523,
            47.647331
          ],
          [
            -122.339395,
            47.647256
          ],
          [
            -122.339235,
            47.647161
          ],
          [
            -122.339085,
            47.647088
          ],
          [
            -122.338882,
            47.646991
          ],
          [
            -122.33869,
            47.646926
          ],
          [
            -122.338466,
            47.64688
          ],
          [
            -122.338115,
            47.646848
          ],
          [
            -122.338032,
            47.646845
          ],
          [
            -122.337987,
            47.646845
          ],
          [
            -122.337691,
            47.646845
          ],
          [
            -122.337557,
            47.646845
          ],
          [
            -122.337463,
            47.646844
          ],
          [
            -122.337149,
            47.646843
          ],
          [
            -122.337145,
            47.646843
          ],
          [
            -122.336426,
            47.64684
          ],
          [
            -122.336373,
            47.64684
          ],
          [
            -122.336339,
            47.64684
          ],
          [
            -122.335986,
            47.646839
          ],
          [
            -122.335405,
            47.646838
          ],
          [
            -122.335175,
            47.646837
          ],
          [
            -122.334498,
            47.646839
          ],
          [
            -122.334501,
            47.646694
          ],
          [
            -122.334511,
            47.646637
          ],
          [
            -122.334538,
            47.646612
          ],
          [
            -122.3347,
            47.646536
          ],
          [
            -122.334959,
            47.646448
          ]
        ],
        "duration_minutes": 19
      },
      "reasoning": "Isaac heads to the outdoor concert, but rides slow and deliberately to avoid heat exhaustion. The evening is cooler, and he can enjoy the scenic route to the park."
    },
    {
      "index": 7,
      "start_time": "2026-06-03T22:08:33.763Z",
      "end_time": "2026-06-03T23:20:52.258Z",
      "activity": "Hang at Gas Works Park during the free outdoor concert, finding a quieter spot away from the big crowds, with water nearby.",
      "activity_type": "leisure",
      "location_name": "Gas Works Park (Wallingford, Seattle)",
      "location": [
        -122.3344,
        47.6457
      ],
      "travel_from_prev": null,
      "reasoning": "Isaac values close friends over big crowds, so he'll find a smaller vantage point to enjoy the music and the clear evening. He stays hydrated and avoids the dense concert throng."
    },
    {
      "index": 8,
      "start_time": "2026-06-03T23:35:52.258Z",
      "end_time": "2026-06-04T00:08:44.301Z",
      "activity": "Leisurely bike ride home to Ravenna, taking the scenic route and enjoying the cool evening air.",
      "activity_type": "commute",
      "location_name": "Home (Ravenna)",
      "location": [
        -122.29749,
        47.67578
      ],
      "travel_from_prev": {
        "mode": "driving",
        "polyline": [
          [
            -122.334959,
            47.646448
          ],
          [
            -122.3347,
            47.646536
          ],
          [
            -122.334538,
            47.646612
          ],
          [
            -122.334511,
            47.646637
          ],
          [
            -122.334501,
            47.646694
          ],
          [
            -122.334498,
            47.646839
          ],
          [
            -122.334341,
            47.64684
          ],
          [
            -122.334292,
            47.64684
          ],
          [
            -122.334173,
            47.646847
          ],
          [
            -122.334068,
            47.646855
          ],
          [
            -122.333974,
            47.646865
          ],
          [
            -122.333908,
            47.646876
          ],
          [
            -122.333881,
            47.646881
          ],
          [
            -122.333851,
            47.646887
          ],
          [
            -122.333828,
            47.646891
          ],
          [
            -122.333747,
            47.646912
          ],
          [
            -122.333707,
            47.646925
          ],
          [
            -122.333676,
            47.646935
          ],
          [
            -122.333659,
            47.646941
          ],
          [
            -122.333646,
            47.646945
          ],
          [
            -122.333548,
            47.646983
          ],
          [
            -122.333456,
            47.647026
          ],
          [
            -122.333418,
            47.647046
          ],
          [
            -122.333368,
            47.647073
          ],
          [
            -122.333286,
            47.647125
          ],
          [
            -122.333243,
            47.647157
          ],
          [
            -122.333239,
            47.64716
          ],
          [
            -122.333211,
            47.647181
          ],
          [
            -122.333142,
            47.64724
          ],
          [
            -122.333079,
            47.647304
          ],
          [
            -122.333025,
            47.64737
          ],
          [
            -122.332933,
            47.647511
          ],
          [
            -122.33269,
            47.647912
          ],
          [
            -122.332641,
            47.64799
          ],
          [
            -122.332548,
            47.64814
          ],
          [
            -122.332284,
            47.648553
          ],
          [
            -122.332016,
            47.648972
          ],
          [
            -122.331955,
            47.649069
          ],
          [
            -122.331844,
            47.649236
          ],
          [
            -122.331621,
            47.649574
          ],
          [
            -122.331393,
            47.64987
          ],
          [
            -122.331363,
            47.649914
          ],
          [
            -122.331261,
            47.650059
          ],
          [
            -122.331071,
            47.650281
          ],
          [
            -122.330903,
            47.650478
          ],
          [
            -122.330514,
            47.650846
          ],
          [
            -122.33042,
            47.650934
          ],
          [
            -122.32987,
            47.651348
          ],
          [
            -122.329425,
            47.651684
          ],
          [
            -122.32937,
            47.651725
          ],
          [
            -122.329338,
            47.65175
          ],
          [
            -122.329321,
            47.651764
          ],
          [
            -122.329215,
            47.651853
          ],
          [
            -122.329014,
            47.65202
          ],
          [
            -122.328857,
            47.652152
          ],
          [
            -122.328597,
            47.652392
          ],
          [
            -122.327789,
            47.65317
          ],
          [
            -122.327662,
            47.65325
          ],
          [
            -122.327522,
            47.653345
          ],
          [
            -122.327433,
            47.653393
          ],
          [
            -122.327349,
            47.653439
          ],
          [
            -122.327073,
            47.653545
          ],
          [
            -122.326844,
            47.653628
          ],
          [
            -122.326505,
            47.65369
          ],
          [
            -122.326254,
            47.653742
          ],
          [
            -122.325992,
            47.653768
          ],
          [
            -122.325915,
            47.653772
          ],
          [
            -122.325722,
            47.653782
          ],
          [
            -122.325429,
            47.653787
          ],
          [
            -122.325426,
            47.653787
          ],
          [
            -122.325203,
            47.653791
          ],
          [
            -122.324787,
            47.653798
          ],
          [
            -122.324714,
            47.653799
          ],
          [
            -122.324691,
            47.653803
          ],
          [
            -122.324592,
            47.653817
          ],
          [
            -122.324503,
            47.653831
          ],
          [
            -122.324464,
            47.653837
          ],
          [
            -122.324379,
            47.65385
          ],
          [
            -122.324171,
            47.653881
          ],
          [
            -122.323562,
            47.65397
          ],
          [
            -122.323168,
            47.654039
          ],
          [
            -122.322959,
            47.654083
          ],
          [
            -122.322835,
            47.654116
          ],
          [
            -122.322772,
            47.654137
          ],
          [
            -122.32272,
            47.654158
          ],
          [
            -122.32266,
            47.654182
          ],
          [
            -122.32261,
            47.654211
          ],
          [
            -122.322572,
            47.654248
          ],
          [
            -122.322549,
            47.654289
          ],
          [
            -122.322542,
            47.654333
          ],
          [
            -122.322541,
            47.654485
          ],
          [
            -122.322542,
            47.654526
          ],
          [
            -122.322542,
            47.654623
          ],
          [
            -122.322542,
            47.654694
          ],
          [
            -122.322542,
            47.654991
          ],
          [
            -122.322543,
            47.655439
          ],
          [
            -122.322543,
            47.655517
          ],
          [
            -122.322225,
            47.655576
          ],
          [
            -122.32205,
            47.655609
          ],
          [
            -122.321613,
            47.655683
          ],
          [
            -122.321311,
            47.655711
          ],
          [
            -122.321103,
            47.65573
          ],
          [
            -122.321013,
            47.655739
          ],
          [
            -122.320955,
            47.655753
          ],
          [
            -122.320922,
            47.655772
          ],
          [
            -122.320902,
            47.655795
          ],
          [
            -122.320868,
            47.655899
          ],
          [
            -122.320871,
            47.656014
          ],
          [
            -122.320871,
            47.656147
          ],
          [
            -122.320869,
            47.656334
          ],
          [
            -122.320865,
            47.656714
          ],
          [
            -122.32085,
            47.656994
          ],
          [
            -122.320836,
            47.657223
          ],
          [
            -122.320834,
            47.657515
          ],
          [
            -122.320836,
            47.657598
          ],
          [
            -122.320848,
            47.657861
          ],
          [
            -122.320847,
            47.658078
          ],
          [
            -122.320843,
            47.658843
          ],
          [
            -122.32084,
            47.659405
          ],
          [
            -122.320839,
            47.659467
          ],
          [
            -122.320839,
            47.65951
          ],
          [
            -122.320837,
            47.660123
          ],
          [
            -122.320837,
            47.660198
          ],
          [
            -122.320801,
            47.660606
          ],
          [
            -122.320795,
            47.660782
          ],
          [
            -122.320807,
            47.66086
          ],
          [
            -122.320807,
            47.66101
          ],
          [
            -122.320801,
            47.661079
          ],
          [
            -122.320792,
            47.661148
          ],
          [
            -122.320783,
            47.661188
          ],
          [
            -122.320763,
            47.661312
          ],
          [
            -122.320739,
            47.661471
          ],
          [
            -122.320737,
            47.661488
          ],
          [
            -122.320737,
            47.661542
          ],
          [
            -122.320739,
            47.661721
          ],
          [
            -122.320766,
            47.661774
          ],
          [
            -122.320799,
            47.661838
          ],
          [
            -122.320841,
            47.66191
          ],
          [
            -122.320936,
            47.662071
          ],
          [
            -122.321036,
            47.662271
          ],
          [
            -122.321333,
            47.662859
          ],
          [
            -122.321379,
            47.662953
          ],
          [
            -122.32142,
            47.663048
          ],
          [
            -122.321458,
            47.663144
          ],
          [
            -122.321491,
            47.663241
          ],
          [
            -122.32152,
            47.663338
          ],
          [
            -122.321545,
            47.663436
          ],
          [
            -122.321566,
            47.663535
          ],
          [
            -122.321583,
            47.663633
          ],
          [
            -122.321594,
            47.663698
          ],
          [
            -122.321625,
            47.66404
          ],
          [
            -122.321639,
            47.664274
          ],
          [
            -122.321681,
            47.664487
          ],
          [
            -122.3218,
            47.664721
          ],
          [
            -122.32178,
            47.665903
          ],
          [
            -122.32176,
            47.667043
          ],
          [
            -122.321757,
            47.667216
          ],
          [
            -122.321757,
            47.667218
          ],
          [
            -122.32173,
            47.668784
          ],
          [
            -122.321732,
            47.66946
          ],
          [
            -122.321729,
            47.669822
          ],
          [
            -122.321607,
            47.670091
          ],
          [
            -122.32153,
            47.6706
          ],
          [
            -122.321396,
            47.671125
          ],
          [
            -122.321225,
            47.671639
          ],
          [
            -122.32106,
            47.672088
          ],
          [
            -122.320825,
            47.672627
          ],
          [
            -122.320728,
            47.672835
          ],
          [
            -122.320663,
            47.672947
          ],
          [
            -122.320604,
            47.673034
          ],
          [
            -122.320518,
            47.673142
          ],
          [
            -122.320438,
            47.673226
          ],
          [
            -122.320255,
            47.673359
          ],
          [
            -122.320193,
            47.673388
          ],
          [
            -122.320078,
            47.673442
          ],
          [
            -122.320067,
            47.673486
          ],
          [
            -122.320045,
            47.673574
          ],
          [
            -122.320041,
            47.67378
          ],
          [
            -122.32004,
            47.673836
          ],
          [
            -122.320038,
            47.673923
          ],
          [
            -122.320039,
            47.67403
          ],
          [
            -122.320041,
            47.674166
          ],
          [
            -122.320043,
            47.674283
          ],
          [
            -122.320051,
            47.674992
          ],
          [
            -122.320055,
            47.675239
          ],
          [
            -122.320055,
            47.67527
          ],
          [
            -122.320058,
            47.675509
          ],
          [
            -122.320061,
            47.67576
          ],
          [
            -122.320063,
            47.675848
          ],
          [
            -122.319943,
            47.675847
          ],
          [
            -122.319852,
            47.675846
          ],
          [
            -122.319648,
            47.675846
          ],
          [
            -122.319528,
            47.675845
          ],
          [
            -122.319436,
            47.675843
          ],
          [
            -122.319393,
            47.675843
          ],
          [
            -122.319166,
            47.675841
          ],
          [
            -122.319047,
            47.675841
          ],
          [
            -122.318777,
            47.675839
          ],
          [
            -122.318707,
            47.675838
          ],
          [
            -122.318022,
            47.675833
          ],
          [
            -122.317926,
            47.675832
          ],
          [
            -122.317858,
            47.675831
          ],
          [
            -122.317785,
            47.67583
          ],
          [
            -122.31767,
            47.675829
          ],
          [
            -122.317499,
            47.675828
          ],
          [
            -122.317455,
            47.675827
          ],
          [
            -122.317383,
            47.675826
          ],
          [
            -122.317271,
            47.675826
          ],
          [
            -122.317012,
            47.675826
          ],
          [
            -122.316939,
            47.675826
          ],
          [
            -122.316765,
            47.675825
          ],
          [
            -122.316538,
            47.675825
          ],
          [
            -122.316128,
            47.675825
          ],
          [
            -122.316084,
            47.675825
          ],
          [
            -122.315784,
            47.675824
          ],
          [
            -122.315679,
            47.675824
          ],
          [
            -122.315563,
            47.675823
          ],
          [
            -122.315357,
            47.675821
          ],
          [
            -122.315353,
            47.675821
          ],
          [
            -122.315339,
            47.675821
          ],
          [
            -122.315289,
            47.675821
          ],
          [
            -122.315212,
            47.67582
          ],
          [
            -122.315134,
            47.675819
          ],
          [
            -122.314922,
            47.675817
          ],
          [
            -122.314819,
            47.675816
          ],
          [
            -122.314544,
            47.675814
          ],
          [
            -122.314534,
            47.675814
          ],
          [
            -122.314475,
            47.675813
          ],
          [
            -122.314349,
            47.675812
          ],
          [
            -122.314267,
            47.675811
          ],
          [
            -122.313948,
            47.675807
          ],
          [
            -122.313753,
            47.675804
          ],
          [
            -122.31324,
            47.675801
          ],
          [
            -122.313218,
            47.6758
          ],
          [
            -122.313142,
            47.6758
          ],
          [
            -122.312684,
            47.675796
          ],
          [
            -122.312544,
            47.675796
          ],
          [
            -122.312501,
            47.675796
          ],
          [
            -122.312077,
            47.675793
          ],
          [
            -122.311943,
            47.675792
          ],
          [
            -122.31182,
            47.675793
          ],
          [
            -122.311403,
            47.675795
          ],
          [
            -122.311039,
            47.675797
          ],
          [
            -122.310952,
            47.675798
          ],
          [
            -122.310865,
            47.675799
          ],
          [
            -122.310777,
            47.675799
          ],
          [
            -122.310336,
            47.675801
          ],
          [
            -122.309794,
            47.675804
          ],
          [
            -122.309261,
            47.67581
          ],
          [
            -122.309087,
            47.675812
          ],
          [
            -122.30906,
            47.675812
          ],
          [
            -122.308824,
            47.675815
          ],
          [
            -122.308721,
            47.675816
          ],
          [
            -122.308632,
            47.675817
          ],
          [
            -122.308376,
            47.67582
          ],
          [
            -122.308191,
            47.675822
          ],
          [
            -122.30804,
            47.675824
          ],
          [
            -122.307801,
            47.675826
          ],
          [
            -122.307656,
            47.675828
          ],
          [
            -122.307283,
            47.675829
          ],
          [
            -122.307101,
            47.67583
          ],
          [
            -122.307084,
            47.67583
          ],
          [
            -122.306851,
            47.67583
          ],
          [
            -122.306662,
            47.67582
          ],
          [
            -122.306557,
            47.675807
          ],
          [
            -122.306442,
            47.675795
          ],
          [
            -122.30625,
            47.675784
          ],
          [
            -122.305999,
            47.675781
          ],
          [
            -122.305863,
            47.67578
          ],
          [
            -122.305488,
            47.675776
          ],
          [
            -122.305476,
            47.675776
          ],
          [
            -122.305173,
            47.675776
          ],
          [
            -122.305129,
            47.675776
          ],
          [
            -122.30496,
            47.675776
          ],
          [
            -122.304513,
            47.675777
          ],
          [
            -122.304433,
            47.675777
          ],
          [
            -122.30424,
            47.675777
          ],
          [
            -122.303931,
            47.675777
          ],
          [
            -122.30382,
            47.675777
          ],
          [
            -122.303713,
            47.675777
          ],
          [
            -122.303193,
            47.675777
          ],
          [
            -122.302953,
            47.675778
          ],
          [
            -122.30286,
            47.675778
          ],
          [
            -122.302762,
            47.675778
          ],
          [
            -122.302632,
            47.675778
          ],
          [
            -122.302429,
            47.675779
          ],
          [
            -122.302145,
            47.675779
          ],
          [
            -122.301744,
            47.675781
          ],
          [
            -122.301689,
            47.675781
          ],
          [
            -122.301578,
            47.675781
          ],
          [
            -122.301254,
            47.675782
          ],
          [
            -122.301245,
            47.675782
          ],
          [
            -122.300927,
            47.675783
          ],
          [
            -122.300799,
            47.675783
          ],
          [
            -122.300664,
            47.675784
          ],
          [
            -122.300534,
            47.675783
          ],
          [
            -122.300231,
            47.675781
          ],
          [
            -122.300216,
            47.675783
          ],
          [
            -122.300139,
            47.675783
          ],
          [
            -122.300096,
            47.675783
          ],
          [
            -122.300071,
            47.675783
          ],
          [
            -122.299741,
            47.675783
          ],
          [
            -122.299612,
            47.675782
          ],
          [
            -122.299513,
            47.675782
          ],
          [
            -122.299336,
            47.675782
          ],
          [
            -122.298545,
            47.675781
          ],
          [
            -122.298414,
            47.675781
          ],
          [
            -122.298409,
            47.675781
          ],
          [
            -122.298219,
            47.675781
          ],
          [
            -122.298079,
            47.675781
          ],
          [
            -122.297706,
            47.67578
          ],
          [
            -122.297496,
            47.675781
          ]
        ],
        "duration_minutes": 15
      },
      "reasoning": "Post-concert ride home is relaxed and scenic—Isaac's preferred way to wind down. The evening is cool enough for a slow, meditative pedal."
    },
    {
      "index": 9,
      "start_time": "2026-06-04T00:08:44.301Z",
      "end_time": "2026-06-04T00:54:45.161Z",
      "activity": "Dinner on the porch: simple pasta with foraged mushrooms and a cold drink, watching the light fade.",
      "activity_type": "meal",
      "location_name": "Home (Ravenna)",
      "location": [
        -122.29749,
        47.67578
      ],
      "travel_from_prev": null,
      "reasoning": "Isaac winds down with his signature quiet dinner ritual. The evening light and cool air provide relief after a hot day, and the mushrooms connect him to his foraging hobby."
    },
    {
      "index": 10,
      "start_time": "2026-06-04T00:54:45.161Z",
      "end_time": "2026-06-04T01:44:03.226Z",
      "activity": "Read on the porch with a book, letting the day settle.",
      "activity_type": "leisure",
      "location_name": "Home (Ravenna)",
      "location": [
        -122.29749,
        47.67578
      ],
      "travel_from_prev": null,
      "reasoning": "Wind-down at home before sleep. Isaac reflects on the day—a solid mix of focused work, heat management, and a low-key concert experience that matched his preference for quiet over crowds."
    },
    {
      "index": 11,
      "start_time": "2026-06-04T01:44:03.226Z",
      "end_time": "2026-06-04T13:00:00.000Z",
      "activity": "Sleep.",
      "activity_type": "sleep",
      "location_name": "Home (Ravenna)",
      "location": [
        -122.29749,
        47.67578
      ],
      "travel_from_prev": null,
      "reasoning": "Isaac sleeps a solid 7+ hours, recovering from the heat and activity. The overnight span ends before 06:00 as required."
    }
  ],
  "diary": "",
  "thought_process": "",
  "end_state": {
    "location": [
      -122.29749,
      47.67578
    ],
    "energy": 40,
    "notes": ""
  },
  "world_event_prompt": "Hot, clear Wednesday hitting 91F by mid-afternoon. Free outdoor concert at Gas Works Park from 6pm draws big crowds. Moderate air quality from distant BC wildfire smoke.",
  "generated_at": "2026-05-30T18:14:32.734Z",
  "stats": {
    "skeleton_attempts": 1,
    "repair_used": false,
    "geocode_misses": 0,
    "route_misses": 0,
    "overflow_fixed_by_shift": 3,
    "overflow_remaining": 0,
    "compressed_to_fit_day": true,
    "compressed_minutes_saved": 478,
    "sleep_beat_synthesized": false,
    "returned_home_before_sleep": true,
    "llm_ms": 0,
    "mapbox_ms": 0,
    "total_ms": 21101
  },
  "_ok": true
}